[
  {
    "timestamp": "2026-03-24T19:17:56.281467+00:00",
    "data": {
      "id_stacji": "149220070",
      "stacja": "Hoczew",
      "rzeka": "Hoczewka",
      "wojewodztwo": "podkarpackie",
      "lon": "22.3283",
      "lat": "49.4239",
      "stan_wody": "103",
      "stan_wody_data_pomiaru": "2026-03-24 19:00:00",
      "temperatura_wody": null,
      "temperatura_wody_data_pomiaru": null,
      "przelyw": "2.05",
      "przeplyw_data": "2026-02-18 09:50:00",
      "zjawisko_lodowe": "0",
      "zjawisko_lodowe_data_pomiaru": "2026-03-11 14:50:00",
      "zjawisko_zarastania": "0",
      "zjawisko_zarastania_data_pomiaru": "2024-08-22 07:00:00"
    }
  },
  {
    "timestamp": "2026-03-24T20:03:11.149850+00:00",
    "data": {
      "id_stacji": "149220070",
      "stacja": "Hoczew",
      "rzeka": "Hoczewka",
      "wojewodztwo": "podkarpackie",
      "lon": "22.3283",
      "lat": "49.4239",
      "stan_wody": "104",
      "stan_wody_data_pomiaru": "2026-03-24 19:30:00",
      "temperatura_wody": null,
      "temperatura_wody_data_pomiaru": null,
      "przelyw": "2.05",
      "przeplyw_data": "2026-02-18 09:50:00",
      "zjawisko_lodowe": "0",
      "zjawisko_lodowe_data_pomiaru": "2026-03-11 14:50:00",
      "zjawisko_zarastania": "0",
      "zjawisko_zarastania_data_pomiaru": "2024-08-22 07:00:00"
    }
  },
  {
    "timestamp": "2026-03-24T21:06:56.972679+00:00",
    "data": {
      "id_stacji": "149220070",
      "stacja": "Hoczew",
      "rzeka": "Hoczewka",
      "wojewodztwo": "podkarpackie",
      "lon": "22.3283",
      "lat": "49.4239",
      "stan_wody": "103",
      "stan_wody_data_pomiaru": "2026-03-24 20:30:00",
      "temperatura_wody": null,
      "temperatura_wody_data_pomiaru": null,
      "przelyw": "2.05",
      "przeplyw_data": "2026-02-18 09:50:00",
      "zjawisko_lodowe": "0",
      "zjawisko_lodowe_data_pomiaru": "2026-03-11 14:50:00",
      "zjawisko_zarastania": "0",
      "zjawisko_zarastania_data_pomiaru": "2024-08-22 07:00:00"
    }
  },
  {
    "timestamp": "2026-03-24T22:01:59.887122+00:00",
    "data": {
      "id_stacji": "149220070",
      "stacja": "Hoczew",
      "rzeka": "Hoczewka",
      "wojewodztwo": "podkarpackie",
      "lon": "22.3283",
      "lat": "49.4239",
      "stan_wody": "103",
      "stan_wody_data_pomiaru": "2026-03-24 21:30:00",
      "temperatura_wody": null,
      "temperatura_wody_data_pomiaru": null,
      "przelyw": "2.05",
      "przeplyw_data": "2026-02-18 09:50:00",
      "zjawisko_lodowe": "0",
      "zjawisko_lodowe_data_pomiaru": "2026-03-11 14:50:00",
      "zjawisko_zarastania": "0",
      "zjawisko_zarastania_data_pomiaru": "2024-08-22 07:00:00"
    }
  },
  {
    "timestamp": "2026-03-24T23:00:08.493384+00:00",
    "data": {
      "id_stacji": "149220070",
      "stacja": "Hoczew",
      "rzeka": "Hoczewka",
      "wojewodztwo": "podkarpackie",
      "lon": "22.3283",
      "lat": "49.4239",
      "stan_wody": "103",
      "stan_wody_data_pomiaru": "2026-03-24 22:30:00",
      "temperatura_wody": null,
      "temperatura_wody_data_pomiaru": null,
      "przelyw": "2.05",
      "przeplyw_data": "2026-02-18 09:50:00",
      "zjawisko_lodowe": "0",
      "zjawisko_lodowe_data_pomiaru": "2026-03-11 14:50:00",
      "zjawisko_zarastania": "0",
      "zjawisko_zarastania_data_pomiaru": "2024-08-22 07:00:00"
    }
  },
  {
    "timestamp": "2026-03-24T23:42:51.951577+00:00",
    "data": {
      "id_stacji": "149220070",
      "stacja": "Hoczew",
      "rzeka": "Hoczewka",
      "wojewodztwo": "podkarpackie",
      "lon": "22.3283",
      "lat": "49.4239",
      "stan_wody": "103",
      "stan_wody_data_pomiaru": "2026-03-24 23:30:00",
      "temperatura_wody": null,
      "temperatura_wody_data_pomiaru": null,
      "przelyw": "2.05",
      "przeplyw_data": "2026-02-18 09:50:00",
      "zjawisko_lodowe": "0",
      "zjawisko_lodowe_data_pomiaru": "2026-03-11 14:50:00",
      "zjawisko_zarastania": "0",
      "zjawisko_zarastania_data_pomiaru": "2024-08-22 07:00:00"
    }
  },
  {
    "timestamp": "2026-03-25T02:47:47.038389+00:00",
    "data": {
      "id_stacji": "149220070",
      "stacja": "Hoczew",
      "rzeka": "Hoczewka",
      "wojewodztwo": "podkarpackie",
      "lon": "22.3283",
      "lat": "49.4239",
      "stan_wody": "103",
      "stan_wody_data_pomiaru": "2026-03-25 02:30:00",
      "temperatura_wody": null,
      "temperatura_wody_data_pomiaru": null,
      "przelyw": "2.05",
      "przeplyw_data": "2026-02-18 09:50:00",
      "zjawisko_lodowe": "0",
      "zjawisko_lodowe_data_pomiaru": "2026-03-11 14:50:00",
      "zjawisko_zarastania": "0",
      "zjawisko_zarastania_data_pomiaru": "2024-08-22 07:00:00"
    }
  },
  {
    "timestamp": "2026-03-25T05:00:09.772323+00:00",
    "data": {
      "id_stacji": "149220070",
      "stacja": "Hoczew",
      "rzeka": "Hoczewka",
      "wojewodztwo": "podkarpackie",
      "lon": "22.3283",
      "lat": "49.4239",
      "stan_wody": "103",
      "stan_wody_data_pomiaru": "2026-03-25 03:50:00",
      "temperatura_wody": null,
      "temperatura_wody_data_pomiaru": null,
      "przelyw": "2.05",
      "przeplyw_data": "2026-02-18 09:50:00",
      "zjawisko_lodowe": "0",
      "zjawisko_lodowe_data_pomiaru": "2026-03-11 14:50:00",
      "zjawisko_zarastania": "0",
      "zjawisko_zarastania_data_pomiaru": "2024-08-22 07:00:00"
    }
  }
]