[
  {
    "timestamp": "2025-08-27T08:05:35.434306+00:00",
    "data": {
      "id_stacji": "150140020",
      "stacja": "Sieniawka",
      "rzeka": "Nysa Łużycka",
      "wojewodztwo": "dolnośląskie",
      "lon": "14.8369",
      "lat": "50.8964",
      "stan_wody": "67",
      "stan_wody_data_pomiaru": "2025-08-27 07:30:00",
      "temperatura_wody": null,
      "temperatura_wody_data_pomiaru": null,
      "przelyw": "4.72",
      "przeplyw_data": "2025-08-27 07:30:00",
      "zjawisko_lodowe": "1",
      "zjawisko_lodowe_data_pomiaru": "2025-02-17 10:00:00",
      "zjawisko_zarastania": "200",
      "zjawisko_zarastania_data_pomiaru": "2025-08-12 09:10:00"
    }
  },
  {
    "timestamp": "2025-08-27T08:16:33.272220+00:00",
    "data": {
      "id_stacji": "150140020",
      "stacja": "Sieniawka",
      "rzeka": "Nysa Łużycka",
      "wojewodztwo": "dolnośląskie",
      "lon": "14.8369",
      "lat": "50.8964",
      "stan_wody": "66",
      "stan_wody_data_pomiaru": "2025-08-27 08:00:00",
      "temperatura_wody": null,
      "temperatura_wody_data_pomiaru": null,
      "przelyw": "4.72",
      "przeplyw_data": "2025-08-27 07:50:00",
      "zjawisko_lodowe": "1",
      "zjawisko_lodowe_data_pomiaru": "2025-02-17 10:00:00",
      "zjawisko_zarastania": "200",
      "zjawisko_zarastania_data_pomiaru": "2025-08-12 09:10:00"
    }
  },
  {
    "timestamp": "2025-08-27T08:43:58.395711+00:00",
    "data": {
      "id_stacji": "150140020",
      "stacja": "Sieniawka",
      "rzeka": "Nysa Łużycka",
      "wojewodztwo": "dolnośląskie",
      "lon": "14.8369",
      "lat": "50.8964",
      "stan_wody": "65",
      "stan_wody_data_pomiaru": "2025-08-27 08:30:00",
      "temperatura_wody": null,
      "temperatura_wody_data_pomiaru": null,
      "przelyw": "4.46",
      "przeplyw_data": "2025-08-27 08:10:00",
      "zjawisko_lodowe": "1",
      "zjawisko_lodowe_data_pomiaru": "2025-02-17 10:00:00",
      "zjawisko_zarastania": "200",
      "zjawisko_zarastania_data_pomiaru": "2025-08-12 09:10:00"
    }
  },
  {
    "timestamp": "2025-08-27T09:19:28.674749+00:00",
    "data": {
      "id_stacji": "150140020",
      "stacja": "Sieniawka",
      "rzeka": "Nysa Łużycka",
      "wojewodztwo": "dolnośląskie",
      "lon": "14.8369",
      "lat": "50.8964",
      "stan_wody": "64",
      "stan_wody_data_pomiaru": "2025-08-27 09:00:00",
      "temperatura_wody": null,
      "temperatura_wody_data_pomiaru": null,
      "przelyw": "4",
      "przeplyw_data": "2025-08-27 08:50:00",
      "zjawisko_lodowe": "1",
      "zjawisko_lodowe_data_pomiaru": "2025-02-17 10:00:00",
      "zjawisko_zarastania": "200",
      "zjawisko_zarastania_data_pomiaru": "2025-08-12 09:10:00"
    }
  },
  {
    "timestamp": "2025-08-27T09:47:44.766448+00:00",
    "data": {
      "id_stacji": "150140020",
      "stacja": "Sieniawka",
      "rzeka": "Nysa Łużycka",
      "wojewodztwo": "dolnośląskie",
      "lon": "14.8369",
      "lat": "50.8964",
      "stan_wody": "64",
      "stan_wody_data_pomiaru": "2025-08-27 09:30:00",
      "temperatura_wody": null,
      "temperatura_wody_data_pomiaru": null,
      "przelyw": "4",
      "przeplyw_data": "2025-08-27 09:10:00",
      "zjawisko_lodowe": "1",
      "zjawisko_lodowe_data_pomiaru": "2025-02-17 10:00:00",
      "zjawisko_zarastania": "200",
      "zjawisko_zarastania_data_pomiaru": "2025-08-12 09:10:00"
    }
  },
  {
    "timestamp": "2025-08-27T10:38:01.881131+00:00",
    "data": {
      "id_stacji": "150140020",
      "stacja": "Sieniawka",
      "rzeka": "Nysa Łużycka",
      "wojewodztwo": "dolnośląskie",
      "lon": "14.8369",
      "lat": "50.8964",
      "stan_wody": "62",
      "stan_wody_data_pomiaru": "2025-08-27 10:00:00",
      "temperatura_wody": null,
      "temperatura_wody_data_pomiaru": null,
      "przelyw": "3.6",
      "przeplyw_data": "2025-08-27 10:10:00",
      "zjawisko_lodowe": "1",
      "zjawisko_lodowe_data_pomiaru": "2025-02-17 10:00:00",
      "zjawisko_zarastania": "200",
      "zjawisko_zarastania_data_pomiaru": "2025-08-12 09:10:00"
    }
  },
  {
    "timestamp": "2025-08-27T11:28:58.461072+00:00",
    "data": {
      "id_stacji": "150140020",
      "stacja": "Sieniawka",
      "rzeka": "Nysa Łużycka",
      "wojewodztwo": "dolnośląskie",
      "lon": "14.8369",
      "lat": "50.8964",
      "stan_wody": "61",
      "stan_wody_data_pomiaru": "2025-08-27 11:00:00",
      "temperatura_wody": null,
      "temperatura_wody_data_pomiaru": null,
      "przelyw": "3.4",
      "przeplyw_data": "2025-08-27 11:10:00",
      "zjawisko_lodowe": "1",
      "zjawisko_lodowe_data_pomiaru": "2025-02-17 10:00:00",
      "zjawisko_zarastania": "200",
      "zjawisko_zarastania_data_pomiaru": "2025-08-12 09:10:00"
    }
  },
  {
    "timestamp": "2025-08-27T11:51:58.835024+00:00",
    "data": {
      "id_stacji": "150140020",
      "stacja": "Sieniawka",
      "rzeka": "Nysa Łużycka",
      "wojewodztwo": "dolnośląskie",
      "lon": "14.8369",
      "lat": "50.8964",
      "stan_wody": "61",
      "stan_wody_data_pomiaru": "2025-08-27 11:30:00",
      "temperatura_wody": null,
      "temperatura_wody_data_pomiaru": null,
      "przelyw": "3.4",
      "przeplyw_data": "2025-08-27 11:30:00",
      "zjawisko_lodowe": "1",
      "zjawisko_lodowe_data_pomiaru": "2025-02-17 10:00:00",
      "zjawisko_zarastania": "200",
      "zjawisko_zarastania_data_pomiaru": "2025-08-12 09:10:00"
    }
  },
  {
    "timestamp": "2025-08-27T12:19:49.455636+00:00",
    "data": {
      "id_stacji": "150140020",
      "stacja": "Sieniawka",
      "rzeka": "Nysa Łużycka",
      "wojewodztwo": "dolnośląskie",
      "lon": "14.8369",
      "lat": "50.8964",
      "stan_wody": "61",
      "stan_wody_data_pomiaru": "2025-08-27 12:00:00",
      "temperatura_wody": null,
      "temperatura_wody_data_pomiaru": null,
      "przelyw": "3.4",
      "przeplyw_data": "2025-08-27 11:50:00",
      "zjawisko_lodowe": "1",
      "zjawisko_lodowe_data_pomiaru": "2025-02-17 10:00:00",
      "zjawisko_zarastania": "200",
      "zjawisko_zarastania_data_pomiaru": "2025-08-12 09:10:00"
    }
  },
  {
    "timestamp": "2025-08-27T12:56:31.743390+00:00",
    "data": {
      "id_stacji": "150140020",
      "stacja": "Sieniawka",
      "rzeka": "Nysa Łużycka",
      "wojewodztwo": "dolnośląskie",
      "lon": "14.8369",
      "lat": "50.8964",
      "stan_wody": "59",
      "stan_wody_data_pomiaru": "2025-08-27 12:30:00",
      "temperatura_wody": null,
      "temperatura_wody_data_pomiaru": null,
      "przelyw": "3",
      "przeplyw_data": "2025-08-27 12:30:00",
      "zjawisko_lodowe": "1",
      "zjawisko_lodowe_data_pomiaru": "2025-02-17 10:00:00",
      "zjawisko_zarastania": "200",
      "zjawisko_zarastania_data_pomiaru": "2025-08-12 09:10:00"
    }
  },
  {
    "timestamp": "2025-08-27T13:32:28.605778+00:00",
    "data": {
      "id_stacji": "150140020",
      "stacja": "Sieniawka",
      "rzeka": "Nysa Łużycka",
      "wojewodztwo": "dolnośląskie",
      "lon": "14.8369",
      "lat": "50.8964",
      "stan_wody": "57",
      "stan_wody_data_pomiaru": "2025-08-27 13:00:00",
      "temperatura_wody": null,
      "temperatura_wody_data_pomiaru": null,
      "przelyw": "2.6",
      "przeplyw_data": "2025-08-27 13:10:00",
      "zjawisko_lodowe": "1",
      "zjawisko_lodowe_data_pomiaru": "2025-02-17 10:00:00",
      "zjawisko_zarastania": "200",
      "zjawisko_zarastania_data_pomiaru": "2025-08-12 09:10:00"
    }
  },
  {
    "timestamp": "2025-08-27T14:23:32.141821+00:00",
    "data": {
      "id_stacji": "150140020",
      "stacja": "Sieniawka",
      "rzeka": "Nysa Łużycka",
      "wojewodztwo": "dolnośląskie",
      "lon": "14.8369",
      "lat": "50.8964",
      "stan_wody": "56",
      "stan_wody_data_pomiaru": "2025-08-27 14:00:00",
      "temperatura_wody": null,
      "temperatura_wody_data_pomiaru": null,
      "przelyw": "2.4",
      "przeplyw_data": "2025-08-27 13:50:00",
      "zjawisko_lodowe": "1",
      "zjawisko_lodowe_data_pomiaru": "2025-02-17 10:00:00",
      "zjawisko_zarastania": "200",
      "zjawisko_zarastania_data_pomiaru": "2025-08-12 09:10:00"
    }
  },
  {
    "timestamp": "2025-08-27T14:44:45.442621+00:00",
    "data": {
      "id_stacji": "150140020",
      "stacja": "Sieniawka",
      "rzeka": "Nysa Łużycka",
      "wojewodztwo": "dolnośląskie",
      "lon": "14.8369",
      "lat": "50.8964",
      "stan_wody": "55",
      "stan_wody_data_pomiaru": "2025-08-27 14:30:00",
      "temperatura_wody": null,
      "temperatura_wody_data_pomiaru": null,
      "przelyw": "2.2",
      "przeplyw_data": "2025-08-27 14:10:00",
      "zjawisko_lodowe": "1",
      "zjawisko_lodowe_data_pomiaru": "2025-02-17 10:00:00",
      "zjawisko_zarastania": "200",
      "zjawisko_zarastania_data_pomiaru": "2025-08-12 09:10:00"
    }
  },
  {
    "timestamp": "2025-08-27T15:25:31.820228+00:00",
    "data": {
      "id_stacji": "150140020",
      "stacja": "Sieniawka",
      "rzeka": "Nysa Łużycka",
      "wojewodztwo": "dolnośląskie",
      "lon": "14.8369",
      "lat": "50.8964",
      "stan_wody": "56",
      "stan_wody_data_pomiaru": "2025-08-27 15:00:00",
      "temperatura_wody": null,
      "temperatura_wody_data_pomiaru": null,
      "przelyw": "2.2",
      "przeplyw_data": "2025-08-27 14:50:00",
      "zjawisko_lodowe": "1",
      "zjawisko_lodowe_data_pomiaru": "2025-02-17 10:00:00",
      "zjawisko_zarastania": "200",
      "zjawisko_zarastania_data_pomiaru": "2025-08-12 09:10:00"
    }
  },
  {
    "timestamp": "2025-08-27T15:43:08.708766+00:00",
    "data": {
      "id_stacji": "150140020",
      "stacja": "Sieniawka",
      "rzeka": "Nysa Łużycka",
      "wojewodztwo": "dolnośląskie",
      "lon": "14.8369",
      "lat": "50.8964",
      "stan_wody": "58",
      "stan_wody_data_pomiaru": "2025-08-27 15:30:00",
      "temperatura_wody": null,
      "temperatura_wody_data_pomiaru": null,
      "przelyw": "2.4",
      "przeplyw_data": "2025-08-27 15:10:00",
      "zjawisko_lodowe": "1",
      "zjawisko_lodowe_data_pomiaru": "2025-02-17 10:00:00",
      "zjawisko_zarastania": "200",
      "zjawisko_zarastania_data_pomiaru": "2025-08-12 09:10:00"
    }
  },
  {
    "timestamp": "2025-08-27T16:30:55.681162+00:00",
    "data": {
      "id_stacji": "150140020",
      "stacja": "Sieniawka",
      "rzeka": "Nysa Łużycka",
      "wojewodztwo": "dolnośląskie",
      "lon": "14.8369",
      "lat": "50.8964",
      "stan_wody": "58",
      "stan_wody_data_pomiaru": "2025-08-27 16:00:00",
      "temperatura_wody": null,
      "temperatura_wody_data_pomiaru": null,
      "przelyw": "2.8",
      "przeplyw_data": "2025-08-27 16:10:00",
      "zjawisko_lodowe": "1",
      "zjawisko_lodowe_data_pomiaru": "2025-02-17 10:00:00",
      "zjawisko_zarastania": "200",
      "zjawisko_zarastania_data_pomiaru": "2025-08-12 09:10:00"
    }
  }
]