[
  {
    "timestamp": "2025-09-26T14:43:09.278760+00:00",
    "data": {
      "id_stacji": "154150040",
      "stacja": "Bardy",
      "rzeka": "Parsęta",
      "wojewodztwo": "zachodniopomorskie",
      "lon": "15.7139",
      "lat": "54.0917",
      "stan_wody": "194",
      "stan_wody_data_pomiaru": "2025-09-26 14:30:00",
      "temperatura_wody": null,
      "temperatura_wody_data_pomiaru": null,
      "przelyw": "15",
      "przeplyw_data": "2025-09-26 13:50:00",
      "zjawisko_lodowe": "0",
      "zjawisko_lodowe_data_pomiaru": "2024-02-16 10:00:00",
      "zjawisko_zarastania": "100",
      "zjawisko_zarastania_data_pomiaru": "2024-10-10 11:00:00"
    }
  },
  {
    "timestamp": "2025-09-26T15:25:03.004656+00:00",
    "data": {
      "id_stacji": "154150040",
      "stacja": "Bardy",
      "rzeka": "Parsęta",
      "wojewodztwo": "zachodniopomorskie",
      "lon": "15.7139",
      "lat": "54.0917",
      "stan_wody": "194",
      "stan_wody_data_pomiaru": "2025-09-26 15:00:00",
      "temperatura_wody": null,
      "temperatura_wody_data_pomiaru": null,
      "przelyw": "15",
      "przeplyw_data": "2025-09-26 14:50:00",
      "zjawisko_lodowe": "0",
      "zjawisko_lodowe_data_pomiaru": "2024-02-16 10:00:00",
      "zjawisko_zarastania": "100",
      "zjawisko_zarastania_data_pomiaru": "2024-10-10 11:00:00"
    }
  },
  {
    "timestamp": "2025-09-26T16:30:09.513824+00:00",
    "data": {
      "id_stacji": "154150040",
      "stacja": "Bardy",
      "rzeka": "Parsęta",
      "wojewodztwo": "zachodniopomorskie",
      "lon": "15.7139",
      "lat": "54.0917",
      "stan_wody": "194",
      "stan_wody_data_pomiaru": "2025-09-26 16:00:00",
      "temperatura_wody": null,
      "temperatura_wody_data_pomiaru": null,
      "przelyw": "15",
      "przeplyw_data": "2025-09-26 16:10:00",
      "zjawisko_lodowe": "0",
      "zjawisko_lodowe_data_pomiaru": "2024-02-16 10:00:00",
      "zjawisko_zarastania": "100",
      "zjawisko_zarastania_data_pomiaru": "2024-10-10 11:00:00"
    }
  },
  {
    "timestamp": "2025-09-26T16:48:29.230722+00:00",
    "data": {
      "id_stacji": "154150040",
      "stacja": "Bardy",
      "rzeka": "Parsęta",
      "wojewodztwo": "zachodniopomorskie",
      "lon": "15.7139",
      "lat": "54.0917",
      "stan_wody": "194",
      "stan_wody_data_pomiaru": "2025-09-26 16:30:00",
      "temperatura_wody": null,
      "temperatura_wody_data_pomiaru": null,
      "przelyw": "15",
      "przeplyw_data": "2025-09-26 16:30:00",
      "zjawisko_lodowe": "0",
      "zjawisko_lodowe_data_pomiaru": "2024-02-16 10:00:00",
      "zjawisko_zarastania": "100",
      "zjawisko_zarastania_data_pomiaru": "2024-10-10 11:00:00"
    }
  },
  {
    "timestamp": "2025-09-26T17:20:16.297760+00:00",
    "data": {
      "id_stacji": "154150040",
      "stacja": "Bardy",
      "rzeka": "Parsęta",
      "wojewodztwo": "zachodniopomorskie",
      "lon": "15.7139",
      "lat": "54.0917",
      "stan_wody": "194",
      "stan_wody_data_pomiaru": "2025-09-26 16:50:00",
      "temperatura_wody": null,
      "temperatura_wody_data_pomiaru": null,
      "przelyw": "15",
      "przeplyw_data": "2025-09-26 16:50:00",
      "zjawisko_lodowe": "0",
      "zjawisko_lodowe_data_pomiaru": "2024-02-16 10:00:00",
      "zjawisko_zarastania": "100",
      "zjawisko_zarastania_data_pomiaru": "2024-10-10 11:00:00"
    }
  },
  {
    "timestamp": "2025-09-26T18:32:14.390456+00:00",
    "data": {
      "id_stacji": "154150040",
      "stacja": "Bardy",
      "rzeka": "Parsęta",
      "wojewodztwo": "zachodniopomorskie",
      "lon": "15.7139",
      "lat": "54.0917",
      "stan_wody": "194",
      "stan_wody_data_pomiaru": "2025-09-26 17:50:00",
      "temperatura_wody": null,
      "temperatura_wody_data_pomiaru": null,
      "przelyw": "15",
      "przeplyw_data": "2025-09-26 18:10:00",
      "zjawisko_lodowe": "0",
      "zjawisko_lodowe_data_pomiaru": "2024-02-16 10:00:00",
      "zjawisko_zarastania": "100",
      "zjawisko_zarastania_data_pomiaru": "2024-10-10 11:00:00"
    }
  },
  {
    "timestamp": "2025-09-26T19:18:15.176115+00:00",
    "data": {
      "id_stacji": "154150040",
      "stacja": "Bardy",
      "rzeka": "Parsęta",
      "wojewodztwo": "zachodniopomorskie",
      "lon": "15.7139",
      "lat": "54.0917",
      "stan_wody": "194",
      "stan_wody_data_pomiaru": "2025-09-26 19:00:00",
      "temperatura_wody": null,
      "temperatura_wody_data_pomiaru": null,
      "przelyw": "15",
      "przeplyw_data": "2025-09-26 18:50:00",
      "zjawisko_lodowe": "0",
      "zjawisko_lodowe_data_pomiaru": "2024-02-16 10:00:00",
      "zjawisko_zarastania": "100",
      "zjawisko_zarastania_data_pomiaru": "2024-10-10 11:00:00"
    }
  },
  {
    "timestamp": "2025-09-26T20:25:40.782662+00:00",
    "data": {
      "id_stacji": "154150040",
      "stacja": "Bardy",
      "rzeka": "Parsęta",
      "wojewodztwo": "zachodniopomorskie",
      "lon": "15.7139",
      "lat": "54.0917",
      "stan_wody": "194",
      "stan_wody_data_pomiaru": "2025-09-26 20:00:00",
      "temperatura_wody": null,
      "temperatura_wody_data_pomiaru": null,
      "przelyw": "14.8",
      "przeplyw_data": "2025-09-26 19:50:00",
      "zjawisko_lodowe": "0",
      "zjawisko_lodowe_data_pomiaru": "2024-02-16 10:00:00",
      "zjawisko_zarastania": "100",
      "zjawisko_zarastania_data_pomiaru": "2024-10-10 11:00:00"
    }
  },
  {
    "timestamp": "2025-09-26T20:42:06.496293+00:00",
    "data": {
      "id_stacji": "154150040",
      "stacja": "Bardy",
      "rzeka": "Parsęta",
      "wojewodztwo": "zachodniopomorskie",
      "lon": "15.7139",
      "lat": "54.0917",
      "stan_wody": "194",
      "stan_wody_data_pomiaru": "2025-09-26 20:30:00",
      "temperatura_wody": null,
      "temperatura_wody_data_pomiaru": null,
      "przelyw": "15",
      "przeplyw_data": "2025-09-26 20:10:00",
      "zjawisko_lodowe": "0",
      "zjawisko_lodowe_data_pomiaru": "2024-02-16 10:00:00",
      "zjawisko_zarastania": "100",
      "zjawisko_zarastania_data_pomiaru": "2024-10-10 11:00:00"
    }
  },
  {
    "timestamp": "2025-09-26T21:20:03.696783+00:00",
    "data": {
      "id_stacji": "154150040",
      "stacja": "Bardy",
      "rzeka": "Parsęta",
      "wojewodztwo": "zachodniopomorskie",
      "lon": "15.7139",
      "lat": "54.0917",
      "stan_wody": "194",
      "stan_wody_data_pomiaru": "2025-09-26 21:00:00",
      "temperatura_wody": null,
      "temperatura_wody_data_pomiaru": null,
      "przelyw": "15",
      "przeplyw_data": "2025-09-26 20:50:00",
      "zjawisko_lodowe": "0",
      "zjawisko_lodowe_data_pomiaru": "2024-02-16 10:00:00",
      "zjawisko_zarastania": "100",
      "zjawisko_zarastania_data_pomiaru": "2024-10-10 11:00:00"
    }
  },
  {
    "timestamp": "2025-09-26T22:21:35.643871+00:00",
    "data": {
      "id_stacji": "154150040",
      "stacja": "Bardy",
      "rzeka": "Parsęta",
      "wojewodztwo": "zachodniopomorskie",
      "lon": "15.7139",
      "lat": "54.0917",
      "stan_wody": "193",
      "stan_wody_data_pomiaru": "2025-09-26 22:00:00",
      "temperatura_wody": null,
      "temperatura_wody_data_pomiaru": null,
      "przelyw": "15",
      "przeplyw_data": "2025-09-26 21:50:00",
      "zjawisko_lodowe": "0",
      "zjawisko_lodowe_data_pomiaru": "2024-02-16 10:00:00",
      "zjawisko_zarastania": "100",
      "zjawisko_zarastania_data_pomiaru": "2024-10-10 11:00:00"
    }
  },
  {
    "timestamp": "2025-09-26T23:20:48.755629+00:00",
    "data": {
      "id_stacji": "154150040",
      "stacja": "Bardy",
      "rzeka": "Parsęta",
      "wojewodztwo": "zachodniopomorskie",
      "lon": "15.7139",
      "lat": "54.0917",
      "stan_wody": "193",
      "stan_wody_data_pomiaru": "2025-09-26 23:00:00",
      "temperatura_wody": null,
      "temperatura_wody_data_pomiaru": null,
      "przelyw": "14.8",
      "przeplyw_data": "2025-09-26 22:50:00",
      "zjawisko_lodowe": "0",
      "zjawisko_lodowe_data_pomiaru": "2024-02-16 10:00:00",
      "zjawisko_zarastania": "100",
      "zjawisko_zarastania_data_pomiaru": "2024-10-10 11:00:00"
    }
  },
  {
    "timestamp": "2025-09-27T01:47:03.187847+00:00",
    "data": {
      "id_stacji": "154150040",
      "stacja": "Bardy",
      "rzeka": "Parsęta",
      "wojewodztwo": "zachodniopomorskie",
      "lon": "15.7139",
      "lat": "54.0917",
      "stan_wody": "193",
      "stan_wody_data_pomiaru": "2025-09-27 01:30:00",
      "temperatura_wody": null,
      "temperatura_wody_data_pomiaru": null,
      "przelyw": "14.8",
      "przeplyw_data": "2025-09-27 01:10:00",
      "zjawisko_lodowe": "0",
      "zjawisko_lodowe_data_pomiaru": "2024-02-16 10:00:00",
      "zjawisko_zarastania": "100",
      "zjawisko_zarastania_data_pomiaru": "2024-10-10 11:00:00"
    }
  },
  {
    "timestamp": "2025-09-27T02:57:42.910489+00:00",
    "data": {
      "id_stacji": "154150040",
      "stacja": "Bardy",
      "rzeka": "Parsęta",
      "wojewodztwo": "zachodniopomorskie",
      "lon": "15.7139",
      "lat": "54.0917",
      "stan_wody": "193",
      "stan_wody_data_pomiaru": "2025-09-27 02:30:00",
      "temperatura_wody": null,
      "temperatura_wody_data_pomiaru": null,
      "przelyw": "14.8",
      "przeplyw_data": "2025-09-27 02:30:00",
      "zjawisko_lodowe": "0",
      "zjawisko_lodowe_data_pomiaru": "2024-02-16 10:00:00",
      "zjawisko_zarastania": "100",
      "zjawisko_zarastania_data_pomiaru": "2024-10-10 11:00:00"
    }
  },
  {
    "timestamp": "2025-09-27T03:32:20.765751+00:00",
    "data": {
      "id_stacji": "154150040",
      "stacja": "Bardy",
      "rzeka": "Parsęta",
      "wojewodztwo": "zachodniopomorskie",
      "lon": "15.7139",
      "lat": "54.0917",
      "stan_wody": "193",
      "stan_wody_data_pomiaru": "2025-09-27 03:00:00",
      "temperatura_wody": null,
      "temperatura_wody_data_pomiaru": null,
      "przelyw": "14.8",
      "przeplyw_data": "2025-09-27 03:10:00",
      "zjawisko_lodowe": "0",
      "zjawisko_lodowe_data_pomiaru": "2024-02-16 10:00:00",
      "zjawisko_zarastania": "100",
      "zjawisko_zarastania_data_pomiaru": "2024-10-10 11:00:00"
    }
  },
  {
    "timestamp": "2025-09-27T04:27:25.054991+00:00",
    "data": {
      "id_stacji": "154150040",
      "stacja": "Bardy",
      "rzeka": "Parsęta",
      "wojewodztwo": "zachodniopomorskie",
      "lon": "15.7139",
      "lat": "54.0917",
      "stan_wody": "193",
      "stan_wody_data_pomiaru": "2025-09-27 04:00:00",
      "temperatura_wody": null,
      "temperatura_wody_data_pomiaru": null,
      "przelyw": "14.8",
      "przeplyw_data": "2025-09-27 03:50:00",
      "zjawisko_lodowe": "0",
      "zjawisko_lodowe_data_pomiaru": "2024-02-16 10:00:00",
      "zjawisko_zarastania": "100",
      "zjawisko_zarastania_data_pomiaru": "2024-10-10 11:00:00"
    }
  },
  {
    "timestamp": "2025-09-27T04:43:45.862610+00:00",
    "data": {
      "id_stacji": "154150040",
      "stacja": "Bardy",
      "rzeka": "Parsęta",
      "wojewodztwo": "zachodniopomorskie",
      "lon": "15.7139",
      "lat": "54.0917",
      "stan_wody": "193",
      "stan_wody_data_pomiaru": "2025-09-27 04:30:00",
      "temperatura_wody": null,
      "temperatura_wody_data_pomiaru": null,
      "przelyw": "14.8",
      "przeplyw_data": "2025-09-27 04:10:00",
      "zjawisko_lodowe": "0",
      "zjawisko_lodowe_data_pomiaru": "2024-02-16 10:00:00",
      "zjawisko_zarastania": "100",
      "zjawisko_zarastania_data_pomiaru": "2024-10-10 11:00:00"
    }
  },
  {
    "timestamp": "2025-09-27T05:22:01.367216+00:00",
    "data": {
      "id_stacji": "154150040",
      "stacja": "Bardy",
      "rzeka": "Parsęta",
      "wojewodztwo": "zachodniopomorskie",
      "lon": "15.7139",
      "lat": "54.0917",
      "stan_wody": "193",
      "stan_wody_data_pomiaru": "2025-09-27 04:50:00",
      "temperatura_wody": null,
      "temperatura_wody_data_pomiaru": null,
      "przelyw": "14.8",
      "przeplyw_data": "2025-09-27 04:50:00",
      "zjawisko_lodowe": "0",
      "zjawisko_lodowe_data_pomiaru": "2024-02-16 10:00:00",
      "zjawisko_zarastania": "100",
      "zjawisko_zarastania_data_pomiaru": "2024-10-10 11:00:00"
    }
  },
  {
    "timestamp": "2025-09-27T06:31:25.060376+00:00",
    "data": {
      "id_stacji": "154150040",
      "stacja": "Bardy",
      "rzeka": "Parsęta",
      "wojewodztwo": "zachodniopomorskie",
      "lon": "15.7139",
      "lat": "54.0917",
      "stan_wody": "193",
      "stan_wody_data_pomiaru": "2025-09-27 06:00:00",
      "temperatura_wody": null,
      "temperatura_wody_data_pomiaru": null,
      "przelyw": "14.8",
      "przeplyw_data": "2025-09-27 06:10:00",
      "zjawisko_lodowe": "0",
      "zjawisko_lodowe_data_pomiaru": "2024-02-16 10:00:00",
      "zjawisko_zarastania": "100",
      "zjawisko_zarastania_data_pomiaru": "2024-10-10 11:00:00"
    }
  },
  {
    "timestamp": "2025-09-27T07:18:50.761344+00:00",
    "data": {
      "id_stacji": "154150040",
      "stacja": "Bardy",
      "rzeka": "Parsęta",
      "wojewodztwo": "zachodniopomorskie",
      "lon": "15.7139",
      "lat": "54.0917",
      "stan_wody": "193",
      "stan_wody_data_pomiaru": "2025-09-27 07:00:00",
      "temperatura_wody": null,
      "temperatura_wody_data_pomiaru": null,
      "przelyw": "14.6",
      "przeplyw_data": "2025-09-27 06:50:00",
      "zjawisko_lodowe": "0",
      "zjawisko_lodowe_data_pomiaru": "2024-02-16 10:00:00",
      "zjawisko_zarastania": "100",
      "zjawisko_zarastania_data_pomiaru": "2024-10-10 11:00:00"
    }
  },
  {
    "timestamp": "2025-09-27T08:27:54.203187+00:00",
    "data": {
      "id_stacji": "154150040",
      "stacja": "Bardy",
      "rzeka": "Parsęta",
      "wojewodztwo": "zachodniopomorskie",
      "lon": "15.7139",
      "lat": "54.0917",
      "stan_wody": "192",
      "stan_wody_data_pomiaru": "2025-09-27 08:00:00",
      "temperatura_wody": null,
      "temperatura_wody_data_pomiaru": null,
      "przelyw": "14.6",
      "przeplyw_data": "2025-09-27 08:10:00",
      "zjawisko_lodowe": "0",
      "zjawisko_lodowe_data_pomiaru": "2024-02-16 10:00:00",
      "zjawisko_zarastania": "100",
      "zjawisko_zarastania_data_pomiaru": "2024-10-10 11:00:00"
    }
  },
  {
    "timestamp": "2025-09-27T08:44:00.709763+00:00",
    "data": {
      "id_stacji": "154150040",
      "stacja": "Bardy",
      "rzeka": "Parsęta",
      "wojewodztwo": "zachodniopomorskie",
      "lon": "15.7139",
      "lat": "54.0917",
      "stan_wody": "193",
      "stan_wody_data_pomiaru": "2025-09-27 08:30:00",
      "temperatura_wody": null,
      "temperatura_wody_data_pomiaru": null,
      "przelyw": "14.6",
      "przeplyw_data": "2025-09-27 08:10:00",
      "zjawisko_lodowe": "0",
      "zjawisko_lodowe_data_pomiaru": "2024-02-16 10:00:00",
      "zjawisko_zarastania": "100",
      "zjawisko_zarastania_data_pomiaru": "2024-10-10 11:00:00"
    }
  },
  {
    "timestamp": "2025-09-27T09:21:21.965245+00:00",
    "data": {
      "id_stacji": "154150040",
      "stacja": "Bardy",
      "rzeka": "Parsęta",
      "wojewodztwo": "zachodniopomorskie",
      "lon": "15.7139",
      "lat": "54.0917",
      "stan_wody": "193",
      "stan_wody_data_pomiaru": "2025-09-27 09:00:00",
      "temperatura_wody": null,
      "temperatura_wody_data_pomiaru": null,
      "przelyw": "14.8",
      "przeplyw_data": "2025-09-27 08:50:00",
      "zjawisko_lodowe": "0",
      "zjawisko_lodowe_data_pomiaru": "2024-02-16 10:00:00",
      "zjawisko_zarastania": "100",
      "zjawisko_zarastania_data_pomiaru": "2024-10-10 11:00:00"
    }
  },
  {
    "timestamp": "2025-09-27T10:22:06.728491+00:00",
    "data": {
      "id_stacji": "154150040",
      "stacja": "Bardy",
      "rzeka": "Parsęta",
      "wojewodztwo": "zachodniopomorskie",
      "lon": "15.7139",
      "lat": "54.0917",
      "stan_wody": "193",
      "stan_wody_data_pomiaru": "2025-09-27 10:00:00",
      "temperatura_wody": null,
      "temperatura_wody_data_pomiaru": null,
      "przelyw": "14.7",
      "przeplyw_data": "2025-09-27 09:50:00",
      "zjawisko_lodowe": "0",
      "zjawisko_lodowe_data_pomiaru": "2024-02-16 10:00:00",
      "zjawisko_zarastania": "100",
      "zjawisko_zarastania_data_pomiaru": "2024-10-10 11:00:00"
    }
  },
  {
    "timestamp": "2025-09-27T11:17:19.240553+00:00",
    "data": {
      "id_stacji": "154150040",
      "stacja": "Bardy",
      "rzeka": "Parsęta",
      "wojewodztwo": "zachodniopomorskie",
      "lon": "15.7139",
      "lat": "54.0917",
      "stan_wody": "192",
      "stan_wody_data_pomiaru": "2025-09-27 11:00:00",
      "temperatura_wody": null,
      "temperatura_wody_data_pomiaru": null,
      "przelyw": "14.9",
      "przeplyw_data": "2025-09-27 10:50:00",
      "zjawisko_lodowe": "0",
      "zjawisko_lodowe_data_pomiaru": "2024-02-16 10:00:00",
      "zjawisko_zarastania": "100",
      "zjawisko_zarastania_data_pomiaru": "2024-10-10 11:00:00"
    }
  },
  {
    "timestamp": "2025-09-27T12:43:30.455133+00:00",
    "data": {
      "id_stacji": "154150040",
      "stacja": "Bardy",
      "rzeka": "Parsęta",
      "wojewodztwo": "zachodniopomorskie",
      "lon": "15.7139",
      "lat": "54.0917",
      "stan_wody": "192",
      "stan_wody_data_pomiaru": "2025-09-27 12:30:00",
      "temperatura_wody": null,
      "temperatura_wody_data_pomiaru": null,
      "przelyw": "14.9",
      "przeplyw_data": "2025-09-27 12:10:00",
      "zjawisko_lodowe": "0",
      "zjawisko_lodowe_data_pomiaru": "2024-02-16 10:00:00",
      "zjawisko_zarastania": "100",
      "zjawisko_zarastania_data_pomiaru": "2024-10-10 11:00:00"
    }
  },
  {
    "timestamp": "2025-09-27T13:24:47.915553+00:00",
    "data": {
      "id_stacji": "154150040",
      "stacja": "Bardy",
      "rzeka": "Parsęta",
      "wojewodztwo": "zachodniopomorskie",
      "lon": "15.7139",
      "lat": "54.0917",
      "stan_wody": "192",
      "stan_wody_data_pomiaru": "2025-09-27 13:00:00",
      "temperatura_wody": null,
      "temperatura_wody_data_pomiaru": null,
      "przelyw": "14.7",
      "przeplyw_data": "2025-09-27 12:50:00",
      "zjawisko_lodowe": "0",
      "zjawisko_lodowe_data_pomiaru": "2024-02-16 10:00:00",
      "zjawisko_zarastania": "100",
      "zjawisko_zarastania_data_pomiaru": "2024-10-10 11:00:00"
    }
  },
  {
    "timestamp": "2025-09-27T14:19:17.460289+00:00",
    "data": {
      "id_stacji": "154150040",
      "stacja": "Bardy",
      "rzeka": "Parsęta",
      "wojewodztwo": "zachodniopomorskie",
      "lon": "15.7139",
      "lat": "54.0917",
      "stan_wody": "192",
      "stan_wody_data_pomiaru": "2025-09-27 14:00:00",
      "temperatura_wody": null,
      "temperatura_wody_data_pomiaru": null,
      "przelyw": "14.7",
      "przeplyw_data": "2025-09-27 13:50:00",
      "zjawisko_lodowe": "0",
      "zjawisko_lodowe_data_pomiaru": "2024-02-16 10:00:00",
      "zjawisko_zarastania": "100",
      "zjawisko_zarastania_data_pomiaru": "2024-10-10 11:00:00"
    }
  },
  {
    "timestamp": "2025-09-27T15:20:31.454633+00:00",
    "data": {
      "id_stacji": "154150040",
      "stacja": "Bardy",
      "rzeka": "Parsęta",
      "wojewodztwo": "zachodniopomorskie",
      "lon": "15.7139",
      "lat": "54.0917",
      "stan_wody": "193",
      "stan_wody_data_pomiaru": "2025-09-27 15:00:00",
      "temperatura_wody": null,
      "temperatura_wody_data_pomiaru": null,
      "przelyw": "14.7",
      "przeplyw_data": "2025-09-27 14:50:00",
      "zjawisko_lodowe": "0",
      "zjawisko_lodowe_data_pomiaru": "2024-02-16 10:00:00",
      "zjawisko_zarastania": "100",
      "zjawisko_zarastania_data_pomiaru": "2024-10-10 11:00:00"
    }
  },
  {
    "timestamp": "2025-09-27T16:26:54.398767+00:00",
    "data": {
      "id_stacji": "154150040",
      "stacja": "Bardy",
      "rzeka": "Parsęta",
      "wojewodztwo": "zachodniopomorskie",
      "lon": "15.7139",
      "lat": "54.0917",
      "stan_wody": "193",
      "stan_wody_data_pomiaru": "2025-09-27 16:00:00",
      "temperatura_wody": null,
      "temperatura_wody_data_pomiaru": null,
      "przelyw": "14.9",
      "przeplyw_data": "2025-09-27 15:50:00",
      "zjawisko_lodowe": "0",
      "zjawisko_lodowe_data_pomiaru": "2024-02-16 10:00:00",
      "zjawisko_zarastania": "100",
      "zjawisko_zarastania_data_pomiaru": "2024-10-10 11:00:00"
    }
  },
  {
    "timestamp": "2025-09-27T16:43:25.296785+00:00",
    "data": {
      "id_stacji": "154150040",
      "stacja": "Bardy",
      "rzeka": "Parsęta",
      "wojewodztwo": "zachodniopomorskie",
      "lon": "15.7139",
      "lat": "54.0917",
      "stan_wody": "192",
      "stan_wody_data_pomiaru": "2025-09-27 16:30:00",
      "temperatura_wody": null,
      "temperatura_wody_data_pomiaru": null,
      "przelyw": "14.7",
      "przeplyw_data": "2025-09-27 16:10:00",
      "zjawisko_lodowe": "0",
      "zjawisko_lodowe_data_pomiaru": "2024-02-16 10:00:00",
      "zjawisko_zarastania": "100",
      "zjawisko_zarastania_data_pomiaru": "2024-10-10 11:00:00"
    }
  },
  {
    "timestamp": "2025-09-27T17:18:10.515562+00:00",
    "data": {
      "id_stacji": "154150040",
      "stacja": "Bardy",
      "rzeka": "Parsęta",
      "wojewodztwo": "zachodniopomorskie",
      "lon": "15.7139",
      "lat": "54.0917",
      "stan_wody": "192",
      "stan_wody_data_pomiaru": "2025-09-27 16:50:00",
      "temperatura_wody": null,
      "temperatura_wody_data_pomiaru": null,
      "przelyw": "14.7",
      "przeplyw_data": "2025-09-27 16:50:00",
      "zjawisko_lodowe": "0",
      "zjawisko_lodowe_data_pomiaru": "2024-02-16 10:00:00",
      "zjawisko_zarastania": "100",
      "zjawisko_zarastania_data_pomiaru": "2024-10-10 11:00:00"
    }
  },
  {
    "timestamp": "2025-09-27T18:30:36.237061+00:00",
    "data": {
      "id_stacji": "154150040",
      "stacja": "Bardy",
      "rzeka": "Parsęta",
      "wojewodztwo": "zachodniopomorskie",
      "lon": "15.7139",
      "lat": "54.0917",
      "stan_wody": "192",
      "stan_wody_data_pomiaru": "2025-09-27 18:00:00",
      "temperatura_wody": null,
      "temperatura_wody_data_pomiaru": null,
      "przelyw": "14.7",
      "przeplyw_data": "2025-09-27 18:10:00",
      "zjawisko_lodowe": "0",
      "zjawisko_lodowe_data_pomiaru": "2024-02-16 10:00:00",
      "zjawisko_zarastania": "100",
      "zjawisko_zarastania_data_pomiaru": "2024-10-10 11:00:00"
    }
  },
  {
    "timestamp": "2025-09-27T19:16:47.992085+00:00",
    "data": {
      "id_stacji": "154150040",
      "stacja": "Bardy",
      "rzeka": "Parsęta",
      "wojewodztwo": "zachodniopomorskie",
      "lon": "15.7139",
      "lat": "54.0917",
      "stan_wody": "192",
      "stan_wody_data_pomiaru": "2025-09-27 19:00:00",
      "temperatura_wody": null,
      "temperatura_wody_data_pomiaru": null,
      "przelyw": "14.7",
      "przeplyw_data": "2025-09-27 18:50:00",
      "zjawisko_lodowe": "0",
      "zjawisko_lodowe_data_pomiaru": "2024-02-16 10:00:00",
      "zjawisko_zarastania": "100",
      "zjawisko_zarastania_data_pomiaru": "2024-10-10 11:00:00"
    }
  },
  {
    "timestamp": "2025-09-27T20:23:46.905157+00:00",
    "data": {
      "id_stacji": "154150040",
      "stacja": "Bardy",
      "rzeka": "Parsęta",
      "wojewodztwo": "zachodniopomorskie",
      "lon": "15.7139",
      "lat": "54.0917",
      "stan_wody": "192",
      "stan_wody_data_pomiaru": "2025-09-27 20:00:00",
      "temperatura_wody": null,
      "temperatura_wody_data_pomiaru": null,
      "przelyw": "14.7",
      "przeplyw_data": "2025-09-27 19:50:00",
      "zjawisko_lodowe": "0",
      "zjawisko_lodowe_data_pomiaru": "2024-02-16 10:00:00",
      "zjawisko_zarastania": "100",
      "zjawisko_zarastania_data_pomiaru": "2024-10-10 11:00:00"
    }
  },
  {
    "timestamp": "2025-09-27T21:19:08.012132+00:00",
    "data": {
      "id_stacji": "154150040",
      "stacja": "Bardy",
      "rzeka": "Parsęta",
      "wojewodztwo": "zachodniopomorskie",
      "lon": "15.7139",
      "lat": "54.0917",
      "stan_wody": "192",
      "stan_wody_data_pomiaru": "2025-09-27 21:00:00",
      "temperatura_wody": null,
      "temperatura_wody_data_pomiaru": null,
      "przelyw": "14.7",
      "przeplyw_data": "2025-09-27 20:50:00",
      "zjawisko_lodowe": "0",
      "zjawisko_lodowe_data_pomiaru": "2024-02-16 10:00:00",
      "zjawisko_zarastania": "100",
      "zjawisko_zarastania_data_pomiaru": "2024-10-10 11:00:00"
    }
  },
  {
    "timestamp": "2025-09-27T22:20:30.293712+00:00",
    "data": {
      "id_stacji": "154150040",
      "stacja": "Bardy",
      "rzeka": "Parsęta",
      "wojewodztwo": "zachodniopomorskie",
      "lon": "15.7139",
      "lat": "54.0917",
      "stan_wody": "192",
      "stan_wody_data_pomiaru": "2025-09-27 22:00:00",
      "temperatura_wody": null,
      "temperatura_wody_data_pomiaru": null,
      "przelyw": "14.7",
      "przeplyw_data": "2025-09-27 21:50:00",
      "zjawisko_lodowe": "0",
      "zjawisko_lodowe_data_pomiaru": "2024-02-16 10:00:00",
      "zjawisko_zarastania": "100",
      "zjawisko_zarastania_data_pomiaru": "2024-10-10 11:00:00"
    }
  },
  {
    "timestamp": "2025-09-27T23:20:32.337061+00:00",
    "data": {
      "id_stacji": "154150040",
      "stacja": "Bardy",
      "rzeka": "Parsęta",
      "wojewodztwo": "zachodniopomorskie",
      "lon": "15.7139",
      "lat": "54.0917",
      "stan_wody": "192",
      "stan_wody_data_pomiaru": "2025-09-27 23:00:00",
      "temperatura_wody": null,
      "temperatura_wody_data_pomiaru": null,
      "przelyw": "14.7",
      "przeplyw_data": "2025-09-27 22:50:00",
      "zjawisko_lodowe": "0",
      "zjawisko_lodowe_data_pomiaru": "2024-02-16 10:00:00",
      "zjawisko_zarastania": "100",
      "zjawisko_zarastania_data_pomiaru": "2024-10-10 11:00:00"
    }
  },
  {
    "timestamp": "2025-09-28T02:00:54.466227+00:00",
    "data": {
      "id_stacji": "154150040",
      "stacja": "Bardy",
      "rzeka": "Parsęta",
      "wojewodztwo": "zachodniopomorskie",
      "lon": "15.7139",
      "lat": "54.0917",
      "stan_wody": "192",
      "stan_wody_data_pomiaru": "2025-09-28 01:30:00",
      "temperatura_wody": null,
      "temperatura_wody_data_pomiaru": null,
      "przelyw": "14.8",
      "przeplyw_data": "2025-09-28 01:30:00",
      "zjawisko_lodowe": "0",
      "zjawisko_lodowe_data_pomiaru": "2024-02-16 10:00:00",
      "zjawisko_zarastania": "100",
      "zjawisko_zarastania_data_pomiaru": "2024-10-10 11:00:00"
    }
  },
  {
    "timestamp": "2025-09-28T03:28:09.322255+00:00",
    "data": {
      "id_stacji": "154150040",
      "stacja": "Bardy",
      "rzeka": "Parsęta",
      "wojewodztwo": "zachodniopomorskie",
      "lon": "15.7139",
      "lat": "54.0917",
      "stan_wody": "192",
      "stan_wody_data_pomiaru": "2025-09-28 03:00:00",
      "temperatura_wody": null,
      "temperatura_wody_data_pomiaru": null,
      "przelyw": "14.8",
      "przeplyw_data": "2025-09-28 03:10:00",
      "zjawisko_lodowe": "0",
      "zjawisko_lodowe_data_pomiaru": "2024-02-16 10:00:00",
      "zjawisko_zarastania": "100",
      "zjawisko_zarastania_data_pomiaru": "2024-10-10 11:00:00"
    }
  },
  {
    "timestamp": "2025-09-28T03:52:12.990660+00:00",
    "data": {
      "id_stacji": "154150040",
      "stacja": "Bardy",
      "rzeka": "Parsęta",
      "wojewodztwo": "zachodniopomorskie",
      "lon": "15.7139",
      "lat": "54.0917",
      "stan_wody": "192",
      "stan_wody_data_pomiaru": "2025-09-28 03:30:00",
      "temperatura_wody": null,
      "temperatura_wody_data_pomiaru": null,
      "przelyw": "14.8",
      "przeplyw_data": "2025-09-28 03:30:00",
      "zjawisko_lodowe": "0",
      "zjawisko_lodowe_data_pomiaru": "2024-02-16 10:00:00",
      "zjawisko_zarastania": "100",
      "zjawisko_zarastania_data_pomiaru": "2024-10-10 11:00:00"
    }
  },
  {
    "timestamp": "2025-09-28T04:27:31.646285+00:00",
    "data": {
      "id_stacji": "154150040",
      "stacja": "Bardy",
      "rzeka": "Parsęta",
      "wojewodztwo": "zachodniopomorskie",
      "lon": "15.7139",
      "lat": "54.0917",
      "stan_wody": "192",
      "stan_wody_data_pomiaru": "2025-09-28 04:00:00",
      "temperatura_wody": null,
      "temperatura_wody_data_pomiaru": null,
      "przelyw": "14.8",
      "przeplyw_data": "2025-09-28 03:50:00",
      "zjawisko_lodowe": "0",
      "zjawisko_lodowe_data_pomiaru": "2024-02-16 10:00:00",
      "zjawisko_zarastania": "100",
      "zjawisko_zarastania_data_pomiaru": "2024-10-10 11:00:00"
    }
  },
  {
    "timestamp": "2025-09-28T04:43:56.741283+00:00",
    "data": {
      "id_stacji": "154150040",
      "stacja": "Bardy",
      "rzeka": "Parsęta",
      "wojewodztwo": "zachodniopomorskie",
      "lon": "15.7139",
      "lat": "54.0917",
      "stan_wody": "192",
      "stan_wody_data_pomiaru": "2025-09-28 04:30:00",
      "temperatura_wody": null,
      "temperatura_wody_data_pomiaru": null,
      "przelyw": "14.8",
      "przeplyw_data": "2025-09-28 04:10:00",
      "zjawisko_lodowe": "0",
      "zjawisko_lodowe_data_pomiaru": "2024-02-16 10:00:00",
      "zjawisko_zarastania": "100",
      "zjawisko_zarastania_data_pomiaru": "2024-10-10 11:00:00"
    }
  },
  {
    "timestamp": "2025-09-28T05:22:26.143532+00:00",
    "data": {
      "id_stacji": "154150040",
      "stacja": "Bardy",
      "rzeka": "Parsęta",
      "wojewodztwo": "zachodniopomorskie",
      "lon": "15.7139",
      "lat": "54.0917",
      "stan_wody": "192",
      "stan_wody_data_pomiaru": "2025-09-28 04:50:00",
      "temperatura_wody": null,
      "temperatura_wody_data_pomiaru": null,
      "przelyw": "14.8",
      "przeplyw_data": "2025-09-28 04:50:00",
      "zjawisko_lodowe": "0",
      "zjawisko_lodowe_data_pomiaru": "2024-02-16 10:00:00",
      "zjawisko_zarastania": "100",
      "zjawisko_zarastania_data_pomiaru": "2024-10-10 11:00:00"
    }
  },
  {
    "timestamp": "2025-09-28T06:33:16.334794+00:00",
    "data": {
      "id_stacji": "154150040",
      "stacja": "Bardy",
      "rzeka": "Parsęta",
      "wojewodztwo": "zachodniopomorskie",
      "lon": "15.7139",
      "lat": "54.0917",
      "stan_wody": "192",
      "stan_wody_data_pomiaru": "2025-09-28 06:00:00",
      "temperatura_wody": null,
      "temperatura_wody_data_pomiaru": null,
      "przelyw": "14.8",
      "przeplyw_data": "2025-09-28 06:10:00",
      "zjawisko_lodowe": "0",
      "zjawisko_lodowe_data_pomiaru": "2024-02-16 10:00:00",
      "zjawisko_zarastania": "100",
      "zjawisko_zarastania_data_pomiaru": "2024-10-10 11:00:00"
    }
  },
  {
    "timestamp": "2025-09-28T07:19:51.076694+00:00",
    "data": {
      "id_stacji": "154150040",
      "stacja": "Bardy",
      "rzeka": "Parsęta",
      "wojewodztwo": "zachodniopomorskie",
      "lon": "15.7139",
      "lat": "54.0917",
      "stan_wody": "191",
      "stan_wody_data_pomiaru": "2025-09-28 07:00:00",
      "temperatura_wody": null,
      "temperatura_wody_data_pomiaru": null,
      "przelyw": "14.8",
      "przeplyw_data": "2025-09-28 06:50:00",
      "zjawisko_lodowe": "0",
      "zjawisko_lodowe_data_pomiaru": "2024-02-16 10:00:00",
      "zjawisko_zarastania": "100",
      "zjawisko_zarastania_data_pomiaru": "2024-10-10 11:00:00"
    }
  },
  {
    "timestamp": "2025-09-28T08:27:40.424068+00:00",
    "data": {
      "id_stacji": "154150040",
      "stacja": "Bardy",
      "rzeka": "Parsęta",
      "wojewodztwo": "zachodniopomorskie",
      "lon": "15.7139",
      "lat": "54.0917",
      "stan_wody": "191",
      "stan_wody_data_pomiaru": "2025-09-28 08:00:00",
      "temperatura_wody": null,
      "temperatura_wody_data_pomiaru": null,
      "przelyw": "14.8",
      "przeplyw_data": "2025-09-28 07:50:00",
      "zjawisko_lodowe": "0",
      "zjawisko_lodowe_data_pomiaru": "2024-02-16 10:00:00",
      "zjawisko_zarastania": "100",
      "zjawisko_zarastania_data_pomiaru": "2024-10-10 11:00:00"
    }
  },
  {
    "timestamp": "2025-09-28T08:44:03.028370+00:00",
    "data": {
      "id_stacji": "154150040",
      "stacja": "Bardy",
      "rzeka": "Parsęta",
      "wojewodztwo": "zachodniopomorskie",
      "lon": "15.7139",
      "lat": "54.0917",
      "stan_wody": "191",
      "stan_wody_data_pomiaru": "2025-09-28 08:20:00",
      "temperatura_wody": null,
      "temperatura_wody_data_pomiaru": null,
      "przelyw": "14.6",
      "przeplyw_data": "2025-09-28 08:10:00",
      "zjawisko_lodowe": "0",
      "zjawisko_lodowe_data_pomiaru": "2024-02-16 10:00:00",
      "zjawisko_zarastania": "100",
      "zjawisko_zarastania_data_pomiaru": "2024-10-10 11:00:00"
    }
  },
  {
    "timestamp": "2025-09-28T09:21:23.363145+00:00",
    "data": {
      "id_stacji": "154150040",
      "stacja": "Bardy",
      "rzeka": "Parsęta",
      "wojewodztwo": "zachodniopomorskie",
      "lon": "15.7139",
      "lat": "54.0917",
      "stan_wody": "191",
      "stan_wody_data_pomiaru": "2025-09-28 09:00:00",
      "temperatura_wody": null,
      "temperatura_wody_data_pomiaru": null,
      "przelyw": "14.6",
      "przeplyw_data": "2025-09-28 08:50:00",
      "zjawisko_lodowe": "0",
      "zjawisko_lodowe_data_pomiaru": "2024-02-16 10:00:00",
      "zjawisko_zarastania": "100",
      "zjawisko_zarastania_data_pomiaru": "2024-10-10 11:00:00"
    }
  },
  {
    "timestamp": "2025-09-28T10:22:02.434801+00:00",
    "data": {
      "id_stacji": "154150040",
      "stacja": "Bardy",
      "rzeka": "Parsęta",
      "wojewodztwo": "zachodniopomorskie",
      "lon": "15.7139",
      "lat": "54.0917",
      "stan_wody": "191",
      "stan_wody_data_pomiaru": "2025-09-28 10:00:00",
      "temperatura_wody": null,
      "temperatura_wody_data_pomiaru": null,
      "przelyw": "14.6",
      "przeplyw_data": "2025-09-28 09:30:00",
      "zjawisko_lodowe": "0",
      "zjawisko_lodowe_data_pomiaru": "2024-02-16 10:00:00",
      "zjawisko_zarastania": "100",
      "zjawisko_zarastania_data_pomiaru": "2024-10-10 11:00:00"
    }
  },
  {
    "timestamp": "2025-09-28T11:17:45.048144+00:00",
    "data": {
      "id_stacji": "154150040",
      "stacja": "Bardy",
      "rzeka": "Parsęta",
      "wojewodztwo": "zachodniopomorskie",
      "lon": "15.7139",
      "lat": "54.0917",
      "stan_wody": "191",
      "stan_wody_data_pomiaru": "2025-09-28 11:00:00",
      "temperatura_wody": null,
      "temperatura_wody_data_pomiaru": null,
      "przelyw": "14.6",
      "przeplyw_data": "2025-09-28 10:50:00",
      "zjawisko_lodowe": "0",
      "zjawisko_lodowe_data_pomiaru": "2024-02-16 10:00:00",
      "zjawisko_zarastania": "100",
      "zjawisko_zarastania_data_pomiaru": "2024-10-10 11:00:00"
    }
  },
  {
    "timestamp": "2025-09-28T12:44:32.530214+00:00",
    "data": {
      "id_stacji": "154150040",
      "stacja": "Bardy",
      "rzeka": "Parsęta",
      "wojewodztwo": "zachodniopomorskie",
      "lon": "15.7139",
      "lat": "54.0917",
      "stan_wody": "191",
      "stan_wody_data_pomiaru": "2025-09-28 12:30:00",
      "temperatura_wody": null,
      "temperatura_wody_data_pomiaru": null,
      "przelyw": "14.6",
      "przeplyw_data": "2025-09-28 12:10:00",
      "zjawisko_lodowe": "0",
      "zjawisko_lodowe_data_pomiaru": "2024-02-16 10:00:00",
      "zjawisko_zarastania": "100",
      "zjawisko_zarastania_data_pomiaru": "2024-10-10 11:00:00"
    }
  },
  {
    "timestamp": "2025-09-28T13:25:15.291063+00:00",
    "data": {
      "id_stacji": "154150040",
      "stacja": "Bardy",
      "rzeka": "Parsęta",
      "wojewodztwo": "zachodniopomorskie",
      "lon": "15.7139",
      "lat": "54.0917",
      "stan_wody": "191",
      "stan_wody_data_pomiaru": "2025-09-28 13:00:00",
      "temperatura_wody": null,
      "temperatura_wody_data_pomiaru": null,
      "przelyw": "14.6",
      "przeplyw_data": "2025-09-28 12:50:00",
      "zjawisko_lodowe": "0",
      "zjawisko_lodowe_data_pomiaru": "2024-02-16 10:00:00",
      "zjawisko_zarastania": "100",
      "zjawisko_zarastania_data_pomiaru": "2024-10-10 11:00:00"
    }
  },
  {
    "timestamp": "2025-09-28T14:18:22.394548+00:00",
    "data": {
      "id_stacji": "154150040",
      "stacja": "Bardy",
      "rzeka": "Parsęta",
      "wojewodztwo": "zachodniopomorskie",
      "lon": "15.7139",
      "lat": "54.0917",
      "stan_wody": "191",
      "stan_wody_data_pomiaru": "2025-09-28 14:00:00",
      "temperatura_wody": null,
      "temperatura_wody_data_pomiaru": null,
      "przelyw": "14.6",
      "przeplyw_data": "2025-09-28 13:50:00",
      "zjawisko_lodowe": "0",
      "zjawisko_lodowe_data_pomiaru": "2024-02-16 10:00:00",
      "zjawisko_zarastania": "100",
      "zjawisko_zarastania_data_pomiaru": "2024-10-10 11:00:00"
    }
  },
  {
    "timestamp": "2025-09-28T15:19:56.719964+00:00",
    "data": {
      "id_stacji": "154150040",
      "stacja": "Bardy",
      "rzeka": "Parsęta",
      "wojewodztwo": "zachodniopomorskie",
      "lon": "15.7139",
      "lat": "54.0917",
      "stan_wody": "191",
      "stan_wody_data_pomiaru": "2025-09-28 15:00:00",
      "temperatura_wody": null,
      "temperatura_wody_data_pomiaru": null,
      "przelyw": "14.6",
      "przeplyw_data": "2025-09-28 14:50:00",
      "zjawisko_lodowe": "0",
      "zjawisko_lodowe_data_pomiaru": "2024-02-16 10:00:00",
      "zjawisko_zarastania": "100",
      "zjawisko_zarastania_data_pomiaru": "2024-10-10 11:00:00"
    }
  },
  {
    "timestamp": "2025-09-28T16:25:56.190841+00:00",
    "data": {
      "id_stacji": "154150040",
      "stacja": "Bardy",
      "rzeka": "Parsęta",
      "wojewodztwo": "zachodniopomorskie",
      "lon": "15.7139",
      "lat": "54.0917",
      "stan_wody": "191",
      "stan_wody_data_pomiaru": "2025-09-28 15:50:00",
      "temperatura_wody": null,
      "temperatura_wody_data_pomiaru": null,
      "przelyw": "14.6",
      "przeplyw_data": "2025-09-28 15:50:00",
      "zjawisko_lodowe": "0",
      "zjawisko_lodowe_data_pomiaru": "2024-02-16 10:00:00",
      "zjawisko_zarastania": "100",
      "zjawisko_zarastania_data_pomiaru": "2024-10-10 11:00:00"
    }
  },
  {
    "timestamp": "2025-09-28T16:42:14.666968+00:00",
    "data": {
      "id_stacji": "154150040",
      "stacja": "Bardy",
      "rzeka": "Parsęta",
      "wojewodztwo": "zachodniopomorskie",
      "lon": "15.7139",
      "lat": "54.0917",
      "stan_wody": "191",
      "stan_wody_data_pomiaru": "2025-09-28 16:30:00",
      "temperatura_wody": null,
      "temperatura_wody_data_pomiaru": null,
      "przelyw": "14.6",
      "przeplyw_data": "2025-09-28 16:10:00",
      "zjawisko_lodowe": "0",
      "zjawisko_lodowe_data_pomiaru": "2024-02-16 10:00:00",
      "zjawisko_zarastania": "100",
      "zjawisko_zarastania_data_pomiaru": "2024-10-10 11:00:00"
    }
  },
  {
    "timestamp": "2025-09-28T17:18:01.872957+00:00",
    "data": {
      "id_stacji": "154150040",
      "stacja": "Bardy",
      "rzeka": "Parsęta",
      "wojewodztwo": "zachodniopomorskie",
      "lon": "15.7139",
      "lat": "54.0917",
      "stan_wody": "191",
      "stan_wody_data_pomiaru": "2025-09-28 16:50:00",
      "temperatura_wody": null,
      "temperatura_wody_data_pomiaru": null,
      "przelyw": "14.6",
      "przeplyw_data": "2025-09-28 16:50:00",
      "zjawisko_lodowe": "0",
      "zjawisko_lodowe_data_pomiaru": "2024-02-16 10:00:00",
      "zjawisko_zarastania": "100",
      "zjawisko_zarastania_data_pomiaru": "2024-10-10 11:00:00"
    }
  },
  {
    "timestamp": "2025-09-28T18:30:07.397920+00:00",
    "data": {
      "id_stacji": "154150040",
      "stacja": "Bardy",
      "rzeka": "Parsęta",
      "wojewodztwo": "zachodniopomorskie",
      "lon": "15.7139",
      "lat": "54.0917",
      "stan_wody": "191",
      "stan_wody_data_pomiaru": "2025-09-28 18:00:00",
      "temperatura_wody": null,
      "temperatura_wody_data_pomiaru": null,
      "przelyw": "14.4",
      "przeplyw_data": "2025-09-28 18:10:00",
      "zjawisko_lodowe": "0",
      "zjawisko_lodowe_data_pomiaru": "2024-02-16 10:00:00",
      "zjawisko_zarastania": "100",
      "zjawisko_zarastania_data_pomiaru": "2024-10-10 11:00:00"
    }
  },
  {
    "timestamp": "2025-09-28T18:46:18.315412+00:00",
    "data": {
      "id_stacji": "154150040",
      "stacja": "Bardy",
      "rzeka": "Parsęta",
      "wojewodztwo": "zachodniopomorskie",
      "lon": "15.7139",
      "lat": "54.0917",
      "stan_wody": "191",
      "stan_wody_data_pomiaru": "2025-09-28 18:30:00",
      "temperatura_wody": null,
      "temperatura_wody_data_pomiaru": null,
      "przelyw": "14.4",
      "przeplyw_data": "2025-09-28 18:10:00",
      "zjawisko_lodowe": "0",
      "zjawisko_lodowe_data_pomiaru": "2024-02-16 10:00:00",
      "zjawisko_zarastania": "100",
      "zjawisko_zarastania_data_pomiaru": "2024-10-10 11:00:00"
    }
  },
  {
    "timestamp": "2025-09-28T19:16:39.658411+00:00",
    "data": {
      "id_stacji": "154150040",
      "stacja": "Bardy",
      "rzeka": "Parsęta",
      "wojewodztwo": "zachodniopomorskie",
      "lon": "15.7139",
      "lat": "54.0917",
      "stan_wody": "191",
      "stan_wody_data_pomiaru": "2025-09-28 19:00:00",
      "temperatura_wody": null,
      "temperatura_wody_data_pomiaru": null,
      "przelyw": "14.6",
      "przeplyw_data": "2025-09-28 18:50:00",
      "zjawisko_lodowe": "0",
      "zjawisko_lodowe_data_pomiaru": "2024-02-16 10:00:00",
      "zjawisko_zarastania": "100",
      "zjawisko_zarastania_data_pomiaru": "2024-10-10 11:00:00"
    }
  },
  {
    "timestamp": "2025-09-28T20:23:52.652418+00:00",
    "data": {
      "id_stacji": "154150040",
      "stacja": "Bardy",
      "rzeka": "Parsęta",
      "wojewodztwo": "zachodniopomorskie",
      "lon": "15.7139",
      "lat": "54.0917",
      "stan_wody": "191",
      "stan_wody_data_pomiaru": "2025-09-28 20:00:00",
      "temperatura_wody": null,
      "temperatura_wody_data_pomiaru": null,
      "przelyw": "14.6",
      "przeplyw_data": "2025-09-28 19:50:00",
      "zjawisko_lodowe": "0",
      "zjawisko_lodowe_data_pomiaru": "2024-02-16 10:00:00",
      "zjawisko_zarastania": "100",
      "zjawisko_zarastania_data_pomiaru": "2024-10-10 11:00:00"
    }
  },
  {
    "timestamp": "2025-09-28T21:19:12.946613+00:00",
    "data": {
      "id_stacji": "154150040",
      "stacja": "Bardy",
      "rzeka": "Parsęta",
      "wojewodztwo": "zachodniopomorskie",
      "lon": "15.7139",
      "lat": "54.0917",
      "stan_wody": "191",
      "stan_wody_data_pomiaru": "2025-09-28 21:00:00",
      "temperatura_wody": null,
      "temperatura_wody_data_pomiaru": null,
      "przelyw": "14.6",
      "przeplyw_data": "2025-09-28 20:50:00",
      "zjawisko_lodowe": "0",
      "zjawisko_lodowe_data_pomiaru": "2024-02-16 10:00:00",
      "zjawisko_zarastania": "100",
      "zjawisko_zarastania_data_pomiaru": "2024-10-10 11:00:00"
    }
  },
  {
    "timestamp": "2025-09-28T22:20:51.255126+00:00",
    "data": {
      "id_stacji": "154150040",
      "stacja": "Bardy",
      "rzeka": "Parsęta",
      "wojewodztwo": "zachodniopomorskie",
      "lon": "15.7139",
      "lat": "54.0917",
      "stan_wody": "191",
      "stan_wody_data_pomiaru": "2025-09-28 22:00:00",
      "temperatura_wody": null,
      "temperatura_wody_data_pomiaru": null,
      "przelyw": "14.6",
      "przeplyw_data": "2025-09-28 21:50:00",
      "zjawisko_lodowe": "0",
      "zjawisko_lodowe_data_pomiaru": "2024-02-16 10:00:00",
      "zjawisko_zarastania": "100",
      "zjawisko_zarastania_data_pomiaru": "2024-10-10 11:00:00"
    }
  },
  {
    "timestamp": "2025-09-28T23:20:49.785850+00:00",
    "data": {
      "id_stacji": "154150040",
      "stacja": "Bardy",
      "rzeka": "Parsęta",
      "wojewodztwo": "zachodniopomorskie",
      "lon": "15.7139",
      "lat": "54.0917",
      "stan_wody": "191",
      "stan_wody_data_pomiaru": "2025-09-28 23:00:00",
      "temperatura_wody": null,
      "temperatura_wody_data_pomiaru": null,
      "przelyw": "14.4",
      "przeplyw_data": "2025-09-28 22:50:00",
      "zjawisko_lodowe": "0",
      "zjawisko_lodowe_data_pomiaru": "2024-02-16 10:00:00",
      "zjawisko_zarastania": "100",
      "zjawisko_zarastania_data_pomiaru": "2024-10-10 11:00:00"
    }
  },
  {
    "timestamp": "2025-09-29T01:54:34.378645+00:00",
    "data": {
      "id_stacji": "154150040",
      "stacja": "Bardy",
      "rzeka": "Parsęta",
      "wojewodztwo": "zachodniopomorskie",
      "lon": "15.7139",
      "lat": "54.0917",
      "stan_wody": "191",
      "stan_wody_data_pomiaru": "2025-09-29 01:30:00",
      "temperatura_wody": null,
      "temperatura_wody_data_pomiaru": null,
      "przelyw": "14.6",
      "przeplyw_data": "2025-09-29 01:30:00",
      "zjawisko_lodowe": "0",
      "zjawisko_lodowe_data_pomiaru": "2024-02-16 10:00:00",
      "zjawisko_zarastania": "100",
      "zjawisko_zarastania_data_pomiaru": "2024-10-10 11:00:00"
    }
  },
  {
    "timestamp": "2025-09-29T03:08:26.090034+00:00",
    "data": {
      "id_stacji": "154150040",
      "stacja": "Bardy",
      "rzeka": "Parsęta",
      "wojewodztwo": "zachodniopomorskie",
      "lon": "15.7139",
      "lat": "54.0917",
      "stan_wody": "191",
      "stan_wody_data_pomiaru": "2025-09-29 02:20:00",
      "temperatura_wody": null,
      "temperatura_wody_data_pomiaru": null,
      "przelyw": "14.6",
      "przeplyw_data": "2025-09-29 02:50:00",
      "zjawisko_lodowe": "0",
      "zjawisko_lodowe_data_pomiaru": "2024-02-16 10:00:00",
      "zjawisko_zarastania": "100",
      "zjawisko_zarastania_data_pomiaru": "2024-10-10 11:00:00"
    }
  },
  {
    "timestamp": "2025-09-29T03:51:56.269670+00:00",
    "data": {
      "id_stacji": "154150040",
      "stacja": "Bardy",
      "rzeka": "Parsęta",
      "wojewodztwo": "zachodniopomorskie",
      "lon": "15.7139",
      "lat": "54.0917",
      "stan_wody": "190",
      "stan_wody_data_pomiaru": "2025-09-29 03:30:00",
      "temperatura_wody": null,
      "temperatura_wody_data_pomiaru": null,
      "przelyw": "14.4",
      "przeplyw_data": "2025-09-29 03:30:00",
      "zjawisko_lodowe": "0",
      "zjawisko_lodowe_data_pomiaru": "2024-02-16 10:00:00",
      "zjawisko_zarastania": "100",
      "zjawisko_zarastania_data_pomiaru": "2024-10-10 11:00:00"
    }
  },
  {
    "timestamp": "2025-09-29T04:29:28.070636+00:00",
    "data": {
      "id_stacji": "154150040",
      "stacja": "Bardy",
      "rzeka": "Parsęta",
      "wojewodztwo": "zachodniopomorskie",
      "lon": "15.7139",
      "lat": "54.0917",
      "stan_wody": "190",
      "stan_wody_data_pomiaru": "2025-09-29 04:00:00",
      "temperatura_wody": null,
      "temperatura_wody_data_pomiaru": null,
      "przelyw": "14.4",
      "przeplyw_data": "2025-09-29 04:10:00",
      "zjawisko_lodowe": "0",
      "zjawisko_lodowe_data_pomiaru": "2024-02-16 10:00:00",
      "zjawisko_zarastania": "100",
      "zjawisko_zarastania_data_pomiaru": "2024-10-10 11:00:00"
    }
  },
  {
    "timestamp": "2025-09-29T04:47:11.066748+00:00",
    "data": {
      "id_stacji": "154150040",
      "stacja": "Bardy",
      "rzeka": "Parsęta",
      "wojewodztwo": "zachodniopomorskie",
      "lon": "15.7139",
      "lat": "54.0917",
      "stan_wody": "190",
      "stan_wody_data_pomiaru": "2025-09-29 04:30:00",
      "temperatura_wody": null,
      "temperatura_wody_data_pomiaru": null,
      "przelyw": "14.4",
      "przeplyw_data": "2025-09-29 04:10:00",
      "zjawisko_lodowe": "0",
      "zjawisko_lodowe_data_pomiaru": "2024-02-16 10:00:00",
      "zjawisko_zarastania": "100",
      "zjawisko_zarastania_data_pomiaru": "2024-10-10 11:00:00"
    }
  },
  {
    "timestamp": "2025-09-29T05:24:30.616080+00:00",
    "data": {
      "id_stacji": "154150040",
      "stacja": "Bardy",
      "rzeka": "Parsęta",
      "wojewodztwo": "zachodniopomorskie",
      "lon": "15.7139",
      "lat": "54.0917",
      "stan_wody": "190",
      "stan_wody_data_pomiaru": "2025-09-29 04:50:00",
      "temperatura_wody": null,
      "temperatura_wody_data_pomiaru": null,
      "przelyw": "14.4",
      "przeplyw_data": "2025-09-29 04:50:00",
      "zjawisko_lodowe": "0",
      "zjawisko_lodowe_data_pomiaru": "2024-02-16 10:00:00",
      "zjawisko_zarastania": "100",
      "zjawisko_zarastania_data_pomiaru": "2024-10-10 11:00:00"
    }
  },
  {
    "timestamp": "2025-09-29T05:42:47.937729+00:00",
    "data": {
      "id_stacji": "154150040",
      "stacja": "Bardy",
      "rzeka": "Parsęta",
      "wojewodztwo": "zachodniopomorskie",
      "lon": "15.7139",
      "lat": "54.0917",
      "stan_wody": "190",
      "stan_wody_data_pomiaru": "2025-09-29 05:30:00",
      "temperatura_wody": null,
      "temperatura_wody_data_pomiaru": null,
      "przelyw": "14.4",
      "przeplyw_data": "2025-09-29 05:10:00",
      "zjawisko_lodowe": "0",
      "zjawisko_lodowe_data_pomiaru": "2024-02-16 10:00:00",
      "zjawisko_zarastania": "100",
      "zjawisko_zarastania_data_pomiaru": "2024-10-10 11:00:00"
    }
  },
  {
    "timestamp": "2025-09-29T06:37:46.686084+00:00",
    "data": {
      "id_stacji": "154150040",
      "stacja": "Bardy",
      "rzeka": "Parsęta",
      "wojewodztwo": "zachodniopomorskie",
      "lon": "15.7139",
      "lat": "54.0917",
      "stan_wody": "190",
      "stan_wody_data_pomiaru": "2025-09-29 06:00:00",
      "temperatura_wody": null,
      "temperatura_wody_data_pomiaru": null,
      "przelyw": "14.4",
      "przeplyw_data": "2025-09-29 06:10:00",
      "zjawisko_lodowe": "0",
      "zjawisko_lodowe_data_pomiaru": "2024-02-16 10:00:00",
      "zjawisko_zarastania": "100",
      "zjawisko_zarastania_data_pomiaru": "2024-10-10 11:00:00"
    }
  },
  {
    "timestamp": "2025-09-29T07:25:14.793222+00:00",
    "data": {
      "id_stacji": "154150040",
      "stacja": "Bardy",
      "rzeka": "Parsęta",
      "wojewodztwo": "zachodniopomorskie",
      "lon": "15.7139",
      "lat": "54.0917",
      "stan_wody": "190",
      "stan_wody_data_pomiaru": "2025-09-29 07:00:00",
      "temperatura_wody": null,
      "temperatura_wody_data_pomiaru": null,
      "przelyw": "14.4",
      "przeplyw_data": "2025-09-29 06:50:00",
      "zjawisko_lodowe": "0",
      "zjawisko_lodowe_data_pomiaru": "2024-02-16 10:00:00",
      "zjawisko_zarastania": "100",
      "zjawisko_zarastania_data_pomiaru": "2024-10-10 11:00:00"
    }
  },
  {
    "timestamp": "2025-09-29T08:35:13.112033+00:00",
    "data": {
      "id_stacji": "154150040",
      "stacja": "Bardy",
      "rzeka": "Parsęta",
      "wojewodztwo": "zachodniopomorskie",
      "lon": "15.7139",
      "lat": "54.0917",
      "stan_wody": "190",
      "stan_wody_data_pomiaru": "2025-09-29 08:00:00",
      "temperatura_wody": null,
      "temperatura_wody_data_pomiaru": null,
      "przelyw": "14.4",
      "przeplyw_data": "2025-09-29 08:10:00",
      "zjawisko_lodowe": "0",
      "zjawisko_lodowe_data_pomiaru": "2024-02-16 10:00:00",
      "zjawisko_zarastania": "100",
      "zjawisko_zarastania_data_pomiaru": "2024-10-10 11:00:00"
    }
  },
  {
    "timestamp": "2025-09-29T09:28:34.956474+00:00",
    "data": {
      "id_stacji": "154150040",
      "stacja": "Bardy",
      "rzeka": "Parsęta",
      "wojewodztwo": "zachodniopomorskie",
      "lon": "15.7139",
      "lat": "54.0917",
      "stan_wody": "190",
      "stan_wody_data_pomiaru": "2025-09-29 09:00:00",
      "temperatura_wody": null,
      "temperatura_wody_data_pomiaru": null,
      "przelyw": "14.4",
      "przeplyw_data": "2025-09-29 09:10:00",
      "zjawisko_lodowe": "0",
      "zjawisko_lodowe_data_pomiaru": "2024-02-16 10:00:00",
      "zjawisko_zarastania": "100",
      "zjawisko_zarastania_data_pomiaru": "2024-10-10 11:00:00"
    }
  },
  {
    "timestamp": "2025-09-29T09:45:37.731731+00:00",
    "data": {
      "id_stacji": "154150040",
      "stacja": "Bardy",
      "rzeka": "Parsęta",
      "wojewodztwo": "zachodniopomorskie",
      "lon": "15.7139",
      "lat": "54.0917",
      "stan_wody": "190",
      "stan_wody_data_pomiaru": "2025-09-29 09:30:00",
      "temperatura_wody": null,
      "temperatura_wody_data_pomiaru": null,
      "przelyw": "14.4",
      "przeplyw_data": "2025-09-29 09:10:00",
      "zjawisko_lodowe": "0",
      "zjawisko_lodowe_data_pomiaru": "2024-02-16 10:00:00",
      "zjawisko_zarastania": "100",
      "zjawisko_zarastania_data_pomiaru": "2024-10-10 11:00:00"
    }
  },
  {
    "timestamp": "2025-09-29T10:26:58.052363+00:00",
    "data": {
      "id_stacji": "154150040",
      "stacja": "Bardy",
      "rzeka": "Parsęta",
      "wojewodztwo": "zachodniopomorskie",
      "lon": "15.7139",
      "lat": "54.0917",
      "stan_wody": "190",
      "stan_wody_data_pomiaru": "2025-09-29 10:00:00",
      "temperatura_wody": null,
      "temperatura_wody_data_pomiaru": null,
      "przelyw": "14.4",
      "przeplyw_data": "2025-09-29 09:50:00",
      "zjawisko_lodowe": "0",
      "zjawisko_lodowe_data_pomiaru": "2024-02-16 10:00:00",
      "zjawisko_zarastania": "100",
      "zjawisko_zarastania_data_pomiaru": "2024-10-10 11:00:00"
    }
  },
  {
    "timestamp": "2025-09-29T10:46:01.724978+00:00",
    "data": {
      "id_stacji": "154150040",
      "stacja": "Bardy",
      "rzeka": "Parsęta",
      "wojewodztwo": "zachodniopomorskie",
      "lon": "15.7139",
      "lat": "54.0917",
      "stan_wody": "190",
      "stan_wody_data_pomiaru": "2025-09-29 10:30:00",
      "temperatura_wody": null,
      "temperatura_wody_data_pomiaru": null,
      "przelyw": "14.4",
      "przeplyw_data": "2025-09-29 09:50:00",
      "zjawisko_lodowe": "0",
      "zjawisko_lodowe_data_pomiaru": "2024-02-16 10:00:00",
      "zjawisko_zarastania": "100",
      "zjawisko_zarastania_data_pomiaru": "2024-10-10 11:00:00"
    }
  },
  {
    "timestamp": "2025-09-29T11:19:46.470138+00:00",
    "data": {
      "id_stacji": "154150040",
      "stacja": "Bardy",
      "rzeka": "Parsęta",
      "wojewodztwo": "zachodniopomorskie",
      "lon": "15.7139",
      "lat": "54.0917",
      "stan_wody": "190",
      "stan_wody_data_pomiaru": "2025-09-29 10:50:00",
      "temperatura_wody": null,
      "temperatura_wody_data_pomiaru": null,
      "przelyw": "14.4",
      "przeplyw_data": "2025-09-29 10:50:00",
      "zjawisko_lodowe": "0",
      "zjawisko_lodowe_data_pomiaru": "2024-02-16 10:00:00",
      "zjawisko_zarastania": "100",
      "zjawisko_zarastania_data_pomiaru": "2024-10-10 11:00:00"
    }
  },
  {
    "timestamp": "2025-09-29T12:53:05.601844+00:00",
    "data": {
      "id_stacji": "154150040",
      "stacja": "Bardy",
      "rzeka": "Parsęta",
      "wojewodztwo": "zachodniopomorskie",
      "lon": "15.7139",
      "lat": "54.0917",
      "stan_wody": "190",
      "stan_wody_data_pomiaru": "2025-09-29 12:00:00",
      "temperatura_wody": null,
      "temperatura_wody_data_pomiaru": null,
      "przelyw": "14.4",
      "przeplyw_data": "2025-09-29 12:10:00",
      "zjawisko_lodowe": "0",
      "zjawisko_lodowe_data_pomiaru": "2024-02-16 10:00:00",
      "zjawisko_zarastania": "100",
      "zjawisko_zarastania_data_pomiaru": "2024-10-10 11:00:00"
    }
  },
  {
    "timestamp": "2025-09-29T13:34:20.478456+00:00",
    "data": {
      "id_stacji": "154150040",
      "stacja": "Bardy",
      "rzeka": "Parsęta",
      "wojewodztwo": "zachodniopomorskie",
      "lon": "15.7139",
      "lat": "54.0917",
      "stan_wody": "190",
      "stan_wody_data_pomiaru": "2025-09-29 12:50:00",
      "temperatura_wody": null,
      "temperatura_wody_data_pomiaru": null,
      "przelyw": "14.4",
      "przeplyw_data": "2025-09-29 12:50:00",
      "zjawisko_lodowe": "0",
      "zjawisko_lodowe_data_pomiaru": "2024-02-16 10:00:00",
      "zjawisko_zarastania": "100",
      "zjawisko_zarastania_data_pomiaru": "2024-10-10 11:00:00"
    }
  },
  {
    "timestamp": "2025-09-29T14:44:17.838815+00:00",
    "data": {
      "id_stacji": "154150040",
      "stacja": "Bardy",
      "rzeka": "Parsęta",
      "wojewodztwo": "zachodniopomorskie",
      "lon": "15.7139",
      "lat": "54.0917",
      "stan_wody": "190",
      "stan_wody_data_pomiaru": "2025-09-29 14:30:00",
      "temperatura_wody": null,
      "temperatura_wody_data_pomiaru": null,
      "przelyw": "14.4",
      "przeplyw_data": "2025-09-29 12:50:00",
      "zjawisko_lodowe": "0",
      "zjawisko_lodowe_data_pomiaru": "2024-02-16 10:00:00",
      "zjawisko_zarastania": "100",
      "zjawisko_zarastania_data_pomiaru": "2024-10-10 11:00:00"
    }
  },
  {
    "timestamp": "2025-09-29T15:25:20.636537+00:00",
    "data": {
      "id_stacji": "154150040",
      "stacja": "Bardy",
      "rzeka": "Parsęta",
      "wojewodztwo": "zachodniopomorskie",
      "lon": "15.7139",
      "lat": "54.0917",
      "stan_wody": "190",
      "stan_wody_data_pomiaru": "2025-09-29 14:50:00",
      "temperatura_wody": null,
      "temperatura_wody_data_pomiaru": null,
      "przelyw": "14.4",
      "przeplyw_data": "2025-09-29 14:50:00",
      "zjawisko_lodowe": "0",
      "zjawisko_lodowe_data_pomiaru": "2024-02-16 10:00:00",
      "zjawisko_zarastania": "100",
      "zjawisko_zarastania_data_pomiaru": "2024-10-10 11:00:00"
    }
  },
  {
    "timestamp": "2025-09-30T09:26:40.556655+00:00",
    "data": {
      "id_stacji": "154150040",
      "stacja": "Bardy",
      "rzeka": "Parsęta",
      "wojewodztwo": "zachodniopomorskie",
      "lon": "15.7139",
      "lat": "54.0917",
      "stan_wody": "190",
      "stan_wody_data_pomiaru": "2025-09-30 08:20:00",
      "temperatura_wody": null,
      "temperatura_wody_data_pomiaru": null,
      "przelyw": "14.4",
      "przeplyw_data": "2025-09-29 19:30:00",
      "zjawisko_lodowe": "0",
      "zjawisko_lodowe_data_pomiaru": "2024-02-16 10:00:00",
      "zjawisko_zarastania": "100",
      "zjawisko_zarastania_data_pomiaru": "2024-10-10 11:00:00"
    }
  },
  {
    "timestamp": "2025-09-30T10:26:43.377257+00:00",
    "data": {
      "id_stacji": "154150040",
      "stacja": "Bardy",
      "rzeka": "Parsęta",
      "wojewodztwo": "zachodniopomorskie",
      "lon": "15.7139",
      "lat": "54.0917",
      "stan_wody": "190",
      "stan_wody_data_pomiaru": "2025-09-30 09:50:00",
      "temperatura_wody": null,
      "temperatura_wody_data_pomiaru": null,
      "przelyw": "14.4",
      "przeplyw_data": "2025-09-30 09:50:00",
      "zjawisko_lodowe": "0",
      "zjawisko_lodowe_data_pomiaru": "2024-02-16 10:00:00",
      "zjawisko_zarastania": "100",
      "zjawisko_zarastania_data_pomiaru": "2024-10-10 11:00:00"
    }
  },
  {
    "timestamp": "2025-10-01T22:22:13.656723+00:00",
    "data": {
      "id_stacji": "154150040",
      "stacja": "Bardy",
      "rzeka": "Parsęta",
      "wojewodztwo": "zachodniopomorskie",
      "lon": "15.7139",
      "lat": "54.0917",
      "stan_wody": "191",
      "stan_wody_data_pomiaru": "2025-10-01 21:50:00",
      "temperatura_wody": null,
      "temperatura_wody_data_pomiaru": null,
      "przelyw": "14.7",
      "przeplyw_data": "2025-10-01 21:50:00",
      "zjawisko_lodowe": "0",
      "zjawisko_lodowe_data_pomiaru": "2024-02-16 10:00:00",
      "zjawisko_zarastania": "100",
      "zjawisko_zarastania_data_pomiaru": "2024-10-10 11:00:00"
    }
  },
  {
    "timestamp": "2025-10-01T23:20:28.845890+00:00",
    "data": {
      "id_stacji": "154150040",
      "stacja": "Bardy",
      "rzeka": "Parsęta",
      "wojewodztwo": "zachodniopomorskie",
      "lon": "15.7139",
      "lat": "54.0917",
      "stan_wody": "191",
      "stan_wody_data_pomiaru": "2025-10-01 22:50:00",
      "temperatura_wody": null,
      "temperatura_wody_data_pomiaru": null,
      "przelyw": "14.7",
      "przeplyw_data": "2025-10-01 22:50:00",
      "zjawisko_lodowe": "0",
      "zjawisko_lodowe_data_pomiaru": "2024-02-16 10:00:00",
      "zjawisko_zarastania": "100",
      "zjawisko_zarastania_data_pomiaru": "2024-10-10 11:00:00"
    }
  },
  {
    "timestamp": "2025-10-02T01:49:40.388689+00:00",
    "data": {
      "id_stacji": "154150040",
      "stacja": "Bardy",
      "rzeka": "Parsęta",
      "wojewodztwo": "zachodniopomorskie",
      "lon": "15.7139",
      "lat": "54.0917",
      "stan_wody": "191",
      "stan_wody_data_pomiaru": "2025-10-02 00:30:00",
      "temperatura_wody": null,
      "temperatura_wody_data_pomiaru": null,
      "przelyw": "14.7",
      "przeplyw_data": "2025-10-02 00:30:00",
      "zjawisko_lodowe": "0",
      "zjawisko_lodowe_data_pomiaru": "2024-02-16 10:00:00",
      "zjawisko_zarastania": "100",
      "zjawisko_zarastania_data_pomiaru": "2024-10-10 11:00:00"
    }
  },
  {
    "timestamp": "2025-10-02T03:00:56.726776+00:00",
    "data": {
      "id_stacji": "154150040",
      "stacja": "Bardy",
      "rzeka": "Parsęta",
      "wojewodztwo": "zachodniopomorskie",
      "lon": "15.7139",
      "lat": "54.0917",
      "stan_wody": "191",
      "stan_wody_data_pomiaru": "2025-10-02 02:30:00",
      "temperatura_wody": null,
      "temperatura_wody_data_pomiaru": null,
      "przelyw": "14.7",
      "przeplyw_data": "2025-10-02 02:30:00",
      "zjawisko_lodowe": "0",
      "zjawisko_lodowe_data_pomiaru": "2024-02-16 10:00:00",
      "zjawisko_zarastania": "100",
      "zjawisko_zarastania_data_pomiaru": "2024-10-10 11:00:00"
    }
  },
  {
    "timestamp": "2025-10-02T03:46:45.887679+00:00",
    "data": {
      "id_stacji": "154150040",
      "stacja": "Bardy",
      "rzeka": "Parsęta",
      "wojewodztwo": "zachodniopomorskie",
      "lon": "15.7139",
      "lat": "54.0917",
      "stan_wody": "190",
      "stan_wody_data_pomiaru": "2025-10-02 03:30:00",
      "temperatura_wody": null,
      "temperatura_wody_data_pomiaru": null,
      "przelyw": "14.7",
      "przeplyw_data": "2025-10-02 03:10:00",
      "zjawisko_lodowe": "0",
      "zjawisko_lodowe_data_pomiaru": "2024-02-16 10:00:00",
      "zjawisko_zarastania": "100",
      "zjawisko_zarastania_data_pomiaru": "2024-10-10 11:00:00"
    }
  },
  {
    "timestamp": "2025-10-02T04:27:45.765024+00:00",
    "data": {
      "id_stacji": "154150040",
      "stacja": "Bardy",
      "rzeka": "Parsęta",
      "wojewodztwo": "zachodniopomorskie",
      "lon": "15.7139",
      "lat": "54.0917",
      "stan_wody": "191",
      "stan_wody_data_pomiaru": "2025-10-02 04:00:00",
      "temperatura_wody": null,
      "temperatura_wody_data_pomiaru": null,
      "przelyw": "14.7",
      "przeplyw_data": "2025-10-02 03:50:00",
      "zjawisko_lodowe": "0",
      "zjawisko_lodowe_data_pomiaru": "2024-02-16 10:00:00",
      "zjawisko_zarastania": "100",
      "zjawisko_zarastania_data_pomiaru": "2024-10-10 11:00:00"
    }
  },
  {
    "timestamp": "2025-10-02T04:43:51.195361+00:00",
    "data": {
      "id_stacji": "154150040",
      "stacja": "Bardy",
      "rzeka": "Parsęta",
      "wojewodztwo": "zachodniopomorskie",
      "lon": "15.7139",
      "lat": "54.0917",
      "stan_wody": "191",
      "stan_wody_data_pomiaru": "2025-10-02 04:30:00",
      "temperatura_wody": null,
      "temperatura_wody_data_pomiaru": null,
      "przelyw": "14.7",
      "przeplyw_data": "2025-10-02 04:10:00",
      "zjawisko_lodowe": "0",
      "zjawisko_lodowe_data_pomiaru": "2024-02-16 10:00:00",
      "zjawisko_zarastania": "100",
      "zjawisko_zarastania_data_pomiaru": "2024-10-10 11:00:00"
    }
  },
  {
    "timestamp": "2025-10-02T05:22:38.739842+00:00",
    "data": {
      "id_stacji": "154150040",
      "stacja": "Bardy",
      "rzeka": "Parsęta",
      "wojewodztwo": "zachodniopomorskie",
      "lon": "15.7139",
      "lat": "54.0917",
      "stan_wody": "191",
      "stan_wody_data_pomiaru": "2025-10-02 04:50:00",
      "temperatura_wody": null,
      "temperatura_wody_data_pomiaru": null,
      "przelyw": "14.7",
      "przeplyw_data": "2025-10-02 04:50:00",
      "zjawisko_lodowe": "0",
      "zjawisko_lodowe_data_pomiaru": "2024-02-16 10:00:00",
      "zjawisko_zarastania": "100",
      "zjawisko_zarastania_data_pomiaru": "2024-10-10 11:00:00"
    }
  },
  {
    "timestamp": "2025-10-02T06:35:18.108299+00:00",
    "data": {
      "id_stacji": "154150040",
      "stacja": "Bardy",
      "rzeka": "Parsęta",
      "wojewodztwo": "zachodniopomorskie",
      "lon": "15.7139",
      "lat": "54.0917",
      "stan_wody": "190",
      "stan_wody_data_pomiaru": "2025-10-02 05:50:00",
      "temperatura_wody": null,
      "temperatura_wody_data_pomiaru": null,
      "przelyw": "14.6",
      "przeplyw_data": "2025-10-02 06:10:00",
      "zjawisko_lodowe": "0",
      "zjawisko_lodowe_data_pomiaru": "2024-02-16 10:00:00",
      "zjawisko_zarastania": "100",
      "zjawisko_zarastania_data_pomiaru": "2024-10-10 11:00:00"
    }
  },
  {
    "timestamp": "2025-10-02T07:22:34.802308+00:00",
    "data": {
      "id_stacji": "154150040",
      "stacja": "Bardy",
      "rzeka": "Parsęta",
      "wojewodztwo": "zachodniopomorskie",
      "lon": "15.7139",
      "lat": "54.0917",
      "stan_wody": "190",
      "stan_wody_data_pomiaru": "2025-10-02 07:00:00",
      "temperatura_wody": null,
      "temperatura_wody_data_pomiaru": null,
      "przelyw": "14.6",
      "przeplyw_data": "2025-10-02 06:50:00",
      "zjawisko_lodowe": "0",
      "zjawisko_lodowe_data_pomiaru": "2024-02-16 10:00:00",
      "zjawisko_zarastania": "100",
      "zjawisko_zarastania_data_pomiaru": "2024-10-10 11:00:00"
    }
  },
  {
    "timestamp": "2025-10-02T08:31:12.050755+00:00",
    "data": {
      "id_stacji": "154150040",
      "stacja": "Bardy",
      "rzeka": "Parsęta",
      "wojewodztwo": "zachodniopomorskie",
      "lon": "15.7139",
      "lat": "54.0917",
      "stan_wody": "191",
      "stan_wody_data_pomiaru": "2025-10-02 07:30:00",
      "temperatura_wody": null,
      "temperatura_wody_data_pomiaru": null,
      "przelyw": "14.7",
      "przeplyw_data": "2025-10-02 07:30:00",
      "zjawisko_lodowe": "0",
      "zjawisko_lodowe_data_pomiaru": "2024-02-16 10:00:00",
      "zjawisko_zarastania": "100",
      "zjawisko_zarastania_data_pomiaru": "2024-10-10 11:00:00"
    }
  },
  {
    "timestamp": "2025-10-02T10:24:35.612337+00:00",
    "data": {
      "id_stacji": "154150040",
      "stacja": "Bardy",
      "rzeka": "Parsęta",
      "wojewodztwo": "zachodniopomorskie",
      "lon": "15.7139",
      "lat": "54.0917",
      "stan_wody": "190",
      "stan_wody_data_pomiaru": "2025-10-02 10:00:00",
      "temperatura_wody": null,
      "temperatura_wody_data_pomiaru": null,
      "przelyw": "14.7",
      "przeplyw_data": "2025-10-02 07:30:00",
      "zjawisko_lodowe": "0",
      "zjawisko_lodowe_data_pomiaru": "2024-02-16 10:00:00",
      "zjawisko_zarastania": "100",
      "zjawisko_zarastania_data_pomiaru": "2024-10-10 11:00:00"
    }
  },
  {
    "timestamp": "2025-10-02T15:42:19.741347+00:00",
    "data": {
      "id_stacji": "154150040",
      "stacja": "Bardy",
      "rzeka": "Parsęta",
      "wojewodztwo": "zachodniopomorskie",
      "lon": "15.7139",
      "lat": "54.0917",
      "stan_wody": "191",
      "stan_wody_data_pomiaru": "2025-10-02 15:30:00",
      "temperatura_wody": null,
      "temperatura_wody_data_pomiaru": null,
      "przelyw": "14.7",
      "przeplyw_data": "2025-10-02 07:30:00",
      "zjawisko_lodowe": "0",
      "zjawisko_lodowe_data_pomiaru": "2024-02-16 10:00:00",
      "zjawisko_zarastania": "100",
      "zjawisko_zarastania_data_pomiaru": "2024-10-10 11:00:00"
    }
  },
  {
    "timestamp": "2025-10-03T12:48:51.388112+00:00",
    "data": {
      "id_stacji": "154150040",
      "stacja": "Bardy",
      "rzeka": "Parsęta",
      "wojewodztwo": "zachodniopomorskie",
      "lon": "15.7139",
      "lat": "54.0917",
      "stan_wody": "191",
      "stan_wody_data_pomiaru": "2025-10-03 12:30:00",
      "temperatura_wody": null,
      "temperatura_wody_data_pomiaru": null,
      "przelyw": "14.8",
      "przeplyw_data": "2025-10-03 12:30:00",
      "zjawisko_lodowe": "0",
      "zjawisko_lodowe_data_pomiaru": "2024-02-16 10:00:00",
      "zjawisko_zarastania": "100",
      "zjawisko_zarastania_data_pomiaru": "2024-10-10 11:00:00"
    }
  },
  {
    "timestamp": "2025-10-03T13:29:59.863289+00:00",
    "data": {
      "id_stacji": "154150040",
      "stacja": "Bardy",
      "rzeka": "Parsęta",
      "wojewodztwo": "zachodniopomorskie",
      "lon": "15.7139",
      "lat": "54.0917",
      "stan_wody": "190",
      "stan_wody_data_pomiaru": "2025-10-03 13:00:00",
      "temperatura_wody": null,
      "temperatura_wody_data_pomiaru": null,
      "przelyw": "14.8",
      "przeplyw_data": "2025-10-03 13:10:00",
      "zjawisko_lodowe": "0",
      "zjawisko_lodowe_data_pomiaru": "2024-02-16 10:00:00",
      "zjawisko_zarastania": "100",
      "zjawisko_zarastania_data_pomiaru": "2024-10-10 11:00:00"
    }
  },
  {
    "timestamp": "2025-10-03T13:44:58.555394+00:00",
    "data": {
      "id_stacji": "154150040",
      "stacja": "Bardy",
      "rzeka": "Parsęta",
      "wojewodztwo": "zachodniopomorskie",
      "lon": "15.7139",
      "lat": "54.0917",
      "stan_wody": "191",
      "stan_wody_data_pomiaru": "2025-10-03 13:30:00",
      "temperatura_wody": null,
      "temperatura_wody_data_pomiaru": null,
      "przelyw": "14.8",
      "przeplyw_data": "2025-10-03 13:10:00",
      "zjawisko_lodowe": "0",
      "zjawisko_lodowe_data_pomiaru": "2024-02-16 10:00:00",
      "zjawisko_zarastania": "100",
      "zjawisko_zarastania_data_pomiaru": "2024-10-10 11:00:00"
    }
  },
  {
    "timestamp": "2025-10-03T14:22:50.501761+00:00",
    "data": {
      "id_stacji": "154150040",
      "stacja": "Bardy",
      "rzeka": "Parsęta",
      "wojewodztwo": "zachodniopomorskie",
      "lon": "15.7139",
      "lat": "54.0917",
      "stan_wody": "191",
      "stan_wody_data_pomiaru": "2025-10-03 14:00:00",
      "temperatura_wody": null,
      "temperatura_wody_data_pomiaru": null,
      "przelyw": "14.8",
      "przeplyw_data": "2025-10-03 13:50:00",
      "zjawisko_lodowe": "0",
      "zjawisko_lodowe_data_pomiaru": "2024-02-16 10:00:00",
      "zjawisko_zarastania": "100",
      "zjawisko_zarastania_data_pomiaru": "2024-10-10 11:00:00"
    }
  }
]