[
  {
    "timestamp": "2025-09-03T09:25:22.057738+00:00",
    "data": {
      "id_stacji": "154220050",
      "stacja": "Jurkiszki",
      "rzeka": "Jarka",
      "wojewodztwo": "warmińsko-mazurskie",
      "lon": "22.3681",
      "lat": "54.3092",
      "stan_wody": "40",
      "stan_wody_data_pomiaru": "2025-07-17 04:00:00",
      "temperatura_wody": null,
      "temperatura_wody_data_pomiaru": null,
      "przelyw": "0.11",
      "przeplyw_data": "2025-07-17 04:20:00",
      "zjawisko_lodowe": "0",
      "zjawisko_lodowe_data_pomiaru": "2025-01-09 10:10:00",
      "zjawisko_zarastania": "211",
      "zjawisko_zarastania_data_pomiaru": "2025-07-23 10:00:00"
    }
  },
  {
    "timestamp": "2025-09-04T10:24:29.914401+00:00",
    "data": {
      "id_stacji": "154220050",
      "stacja": "Jurkiszki",
      "rzeka": "Jarka",
      "wojewodztwo": "warmińsko-mazurskie",
      "lon": "22.3681",
      "lat": "54.3092",
      "stan_wody": "50",
      "stan_wody_data_pomiaru": "2025-09-04 10:00:00",
      "temperatura_wody": null,
      "temperatura_wody_data_pomiaru": null,
      "przelyw": "0.23",
      "przeplyw_data": "2025-09-04 09:50:00",
      "zjawisko_lodowe": "0",
      "zjawisko_lodowe_data_pomiaru": "2025-01-09 10:10:00",
      "zjawisko_zarastania": "211",
      "zjawisko_zarastania_data_pomiaru": "2025-07-23 10:00:00"
    }
  },
  {
    "timestamp": "2025-09-04T10:42:35.886186+00:00",
    "data": {
      "id_stacji": "154220050",
      "stacja": "Jurkiszki",
      "rzeka": "Jarka",
      "wojewodztwo": "warmińsko-mazurskie",
      "lon": "22.3681",
      "lat": "54.3092",
      "stan_wody": "50",
      "stan_wody_data_pomiaru": "2025-09-04 10:30:00",
      "temperatura_wody": null,
      "temperatura_wody_data_pomiaru": null,
      "przelyw": "0.23",
      "przeplyw_data": "2025-09-04 10:10:00",
      "zjawisko_lodowe": "0",
      "zjawisko_lodowe_data_pomiaru": "2025-01-09 10:10:00",
      "zjawisko_zarastania": "211",
      "zjawisko_zarastania_data_pomiaru": "2025-07-23 10:00:00"
    }
  },
  {
    "timestamp": "2025-09-04T11:19:09.770898+00:00",
    "data": {
      "id_stacji": "154220050",
      "stacja": "Jurkiszki",
      "rzeka": "Jarka",
      "wojewodztwo": "warmińsko-mazurskie",
      "lon": "22.3681",
      "lat": "54.3092",
      "stan_wody": "50",
      "stan_wody_data_pomiaru": "2025-09-04 11:00:00",
      "temperatura_wody": null,
      "temperatura_wody_data_pomiaru": null,
      "przelyw": "0.23",
      "przeplyw_data": "2025-09-04 10:50:00",
      "zjawisko_lodowe": "0",
      "zjawisko_lodowe_data_pomiaru": "2025-01-09 10:10:00",
      "zjawisko_zarastania": "211",
      "zjawisko_zarastania_data_pomiaru": "2025-07-23 10:00:00"
    }
  },
  {
    "timestamp": "2025-09-04T12:47:56.301430+00:00",
    "data": {
      "id_stacji": "154220050",
      "stacja": "Jurkiszki",
      "rzeka": "Jarka",
      "wojewodztwo": "warmińsko-mazurskie",
      "lon": "22.3681",
      "lat": "54.3092",
      "stan_wody": "50",
      "stan_wody_data_pomiaru": "2025-09-04 12:30:00",
      "temperatura_wody": null,
      "temperatura_wody_data_pomiaru": null,
      "przelyw": "0.23",
      "przeplyw_data": "2025-09-04 12:30:00",
      "zjawisko_lodowe": "0",
      "zjawisko_lodowe_data_pomiaru": "2025-01-09 10:10:00",
      "zjawisko_zarastania": "211",
      "zjawisko_zarastania_data_pomiaru": "2025-07-23 10:00:00"
    }
  },
  {
    "timestamp": "2025-09-04T13:31:25.240337+00:00",
    "data": {
      "id_stacji": "154220050",
      "stacja": "Jurkiszki",
      "rzeka": "Jarka",
      "wojewodztwo": "warmińsko-mazurskie",
      "lon": "22.3681",
      "lat": "54.3092",
      "stan_wody": "50",
      "stan_wody_data_pomiaru": "2025-09-04 13:00:00",
      "temperatura_wody": null,
      "temperatura_wody_data_pomiaru": null,
      "przelyw": "0.23",
      "przeplyw_data": "2025-09-04 13:10:00",
      "zjawisko_lodowe": "0",
      "zjawisko_lodowe_data_pomiaru": "2025-01-09 10:10:00",
      "zjawisko_zarastania": "211",
      "zjawisko_zarastania_data_pomiaru": "2025-07-23 10:00:00"
    }
  },
  {
    "timestamp": "2025-09-04T14:23:07.948801+00:00",
    "data": {
      "id_stacji": "154220050",
      "stacja": "Jurkiszki",
      "rzeka": "Jarka",
      "wojewodztwo": "warmińsko-mazurskie",
      "lon": "22.3681",
      "lat": "54.3092",
      "stan_wody": "50",
      "stan_wody_data_pomiaru": "2025-09-04 14:00:00",
      "temperatura_wody": null,
      "temperatura_wody_data_pomiaru": null,
      "przelyw": "0.23",
      "przeplyw_data": "2025-09-04 13:50:00",
      "zjawisko_lodowe": "0",
      "zjawisko_lodowe_data_pomiaru": "2025-01-09 10:10:00",
      "zjawisko_zarastania": "211",
      "zjawisko_zarastania_data_pomiaru": "2025-07-23 10:00:00"
    }
  },
  {
    "timestamp": "2025-09-04T14:44:14.937766+00:00",
    "data": {
      "id_stacji": "154220050",
      "stacja": "Jurkiszki",
      "rzeka": "Jarka",
      "wojewodztwo": "warmińsko-mazurskie",
      "lon": "22.3681",
      "lat": "54.3092",
      "stan_wody": "50",
      "stan_wody_data_pomiaru": "2025-09-04 14:30:00",
      "temperatura_wody": null,
      "temperatura_wody_data_pomiaru": null,
      "przelyw": "0.23",
      "przeplyw_data": "2025-09-04 14:10:00",
      "zjawisko_lodowe": "0",
      "zjawisko_lodowe_data_pomiaru": "2025-01-09 10:10:00",
      "zjawisko_zarastania": "211",
      "zjawisko_zarastania_data_pomiaru": "2025-07-23 10:00:00"
    }
  },
  {
    "timestamp": "2025-09-04T15:24:57.120123+00:00",
    "data": {
      "id_stacji": "154220050",
      "stacja": "Jurkiszki",
      "rzeka": "Jarka",
      "wojewodztwo": "warmińsko-mazurskie",
      "lon": "22.3681",
      "lat": "54.3092",
      "stan_wody": "50",
      "stan_wody_data_pomiaru": "2025-09-04 15:00:00",
      "temperatura_wody": null,
      "temperatura_wody_data_pomiaru": null,
      "przelyw": "0.23",
      "przeplyw_data": "2025-09-04 14:50:00",
      "zjawisko_lodowe": "0",
      "zjawisko_lodowe_data_pomiaru": "2025-01-09 10:10:00",
      "zjawisko_zarastania": "211",
      "zjawisko_zarastania_data_pomiaru": "2025-07-23 10:00:00"
    }
  },
  {
    "timestamp": "2025-09-04T15:43:11.333583+00:00",
    "data": {
      "id_stacji": "154220050",
      "stacja": "Jurkiszki",
      "rzeka": "Jarka",
      "wojewodztwo": "warmińsko-mazurskie",
      "lon": "22.3681",
      "lat": "54.3092",
      "stan_wody": "50",
      "stan_wody_data_pomiaru": "2025-09-04 15:30:00",
      "temperatura_wody": null,
      "temperatura_wody_data_pomiaru": null,
      "przelyw": "0.23",
      "przeplyw_data": "2025-09-04 15:10:00",
      "zjawisko_lodowe": "0",
      "zjawisko_lodowe_data_pomiaru": "2025-01-09 10:10:00",
      "zjawisko_zarastania": "211",
      "zjawisko_zarastania_data_pomiaru": "2025-07-23 10:00:00"
    }
  },
  {
    "timestamp": "2025-09-04T16:30:07.620676+00:00",
    "data": {
      "id_stacji": "154220050",
      "stacja": "Jurkiszki",
      "rzeka": "Jarka",
      "wojewodztwo": "warmińsko-mazurskie",
      "lon": "22.3681",
      "lat": "54.3092",
      "stan_wody": "50",
      "stan_wody_data_pomiaru": "2025-09-04 16:00:00",
      "temperatura_wody": null,
      "temperatura_wody_data_pomiaru": null,
      "przelyw": "0.23",
      "przeplyw_data": "2025-09-04 16:10:00",
      "zjawisko_lodowe": "0",
      "zjawisko_lodowe_data_pomiaru": "2025-01-09 10:10:00",
      "zjawisko_zarastania": "211",
      "zjawisko_zarastania_data_pomiaru": "2025-07-23 10:00:00"
    }
  },
  {
    "timestamp": "2025-09-04T16:49:15.574932+00:00",
    "data": {
      "id_stacji": "154220050",
      "stacja": "Jurkiszki",
      "rzeka": "Jarka",
      "wojewodztwo": "warmińsko-mazurskie",
      "lon": "22.3681",
      "lat": "54.3092",
      "stan_wody": "50",
      "stan_wody_data_pomiaru": "2025-09-04 16:30:00",
      "temperatura_wody": null,
      "temperatura_wody_data_pomiaru": null,
      "przelyw": "0.23",
      "przeplyw_data": "2025-09-04 16:30:00",
      "zjawisko_lodowe": "0",
      "zjawisko_lodowe_data_pomiaru": "2025-01-09 10:10:00",
      "zjawisko_zarastania": "211",
      "zjawisko_zarastania_data_pomiaru": "2025-07-23 10:00:00"
    }
  },
  {
    "timestamp": "2025-09-04T17:20:15.480603+00:00",
    "data": {
      "id_stacji": "154220050",
      "stacja": "Jurkiszki",
      "rzeka": "Jarka",
      "wojewodztwo": "warmińsko-mazurskie",
      "lon": "22.3681",
      "lat": "54.3092",
      "stan_wody": "50",
      "stan_wody_data_pomiaru": "2025-09-04 17:00:00",
      "temperatura_wody": null,
      "temperatura_wody_data_pomiaru": null,
      "przelyw": "0.23",
      "przeplyw_data": "2025-09-04 16:50:00",
      "zjawisko_lodowe": "0",
      "zjawisko_lodowe_data_pomiaru": "2025-01-09 10:10:00",
      "zjawisko_zarastania": "211",
      "zjawisko_zarastania_data_pomiaru": "2025-07-23 10:00:00"
    }
  },
  {
    "timestamp": "2025-09-04T18:33:16.948867+00:00",
    "data": {
      "id_stacji": "154220050",
      "stacja": "Jurkiszki",
      "rzeka": "Jarka",
      "wojewodztwo": "warmińsko-mazurskie",
      "lon": "22.3681",
      "lat": "54.3092",
      "stan_wody": "50",
      "stan_wody_data_pomiaru": "2025-09-04 18:00:00",
      "temperatura_wody": null,
      "temperatura_wody_data_pomiaru": null,
      "przelyw": "0.23",
      "przeplyw_data": "2025-09-04 18:10:00",
      "zjawisko_lodowe": "0",
      "zjawisko_lodowe_data_pomiaru": "2025-01-09 10:10:00",
      "zjawisko_zarastania": "211",
      "zjawisko_zarastania_data_pomiaru": "2025-07-23 10:00:00"
    }
  },
  {
    "timestamp": "2025-09-04T19:18:03.954546+00:00",
    "data": {
      "id_stacji": "154220050",
      "stacja": "Jurkiszki",
      "rzeka": "Jarka",
      "wojewodztwo": "warmińsko-mazurskie",
      "lon": "22.3681",
      "lat": "54.3092",
      "stan_wody": "50",
      "stan_wody_data_pomiaru": "2025-09-04 19:00:00",
      "temperatura_wody": null,
      "temperatura_wody_data_pomiaru": null,
      "przelyw": "0.23",
      "przeplyw_data": "2025-09-04 18:50:00",
      "zjawisko_lodowe": "0",
      "zjawisko_lodowe_data_pomiaru": "2025-01-09 10:10:00",
      "zjawisko_zarastania": "211",
      "zjawisko_zarastania_data_pomiaru": "2025-07-23 10:00:00"
    }
  },
  {
    "timestamp": "2025-09-04T20:25:04.526219+00:00",
    "data": {
      "id_stacji": "154220050",
      "stacja": "Jurkiszki",
      "rzeka": "Jarka",
      "wojewodztwo": "warmińsko-mazurskie",
      "lon": "22.3681",
      "lat": "54.3092",
      "stan_wody": "50",
      "stan_wody_data_pomiaru": "2025-09-04 20:00:00",
      "temperatura_wody": null,
      "temperatura_wody_data_pomiaru": null,
      "przelyw": "0.23",
      "przeplyw_data": "2025-09-04 19:50:00",
      "zjawisko_lodowe": "0",
      "zjawisko_lodowe_data_pomiaru": "2025-01-09 10:10:00",
      "zjawisko_zarastania": "211",
      "zjawisko_zarastania_data_pomiaru": "2025-07-23 10:00:00"
    }
  },
  {
    "timestamp": "2025-09-04T21:21:28.693165+00:00",
    "data": {
      "id_stacji": "154220050",
      "stacja": "Jurkiszki",
      "rzeka": "Jarka",
      "wojewodztwo": "warmińsko-mazurskie",
      "lon": "22.3681",
      "lat": "54.3092",
      "stan_wody": "50",
      "stan_wody_data_pomiaru": "2025-09-04 21:00:00",
      "temperatura_wody": null,
      "temperatura_wody_data_pomiaru": null,
      "przelyw": "0.23",
      "przeplyw_data": "2025-09-04 20:50:00",
      "zjawisko_lodowe": "0",
      "zjawisko_lodowe_data_pomiaru": "2025-01-09 10:10:00",
      "zjawisko_zarastania": "211",
      "zjawisko_zarastania_data_pomiaru": "2025-07-23 10:00:00"
    }
  },
  {
    "timestamp": "2025-09-04T22:22:06.024876+00:00",
    "data": {
      "id_stacji": "154220050",
      "stacja": "Jurkiszki",
      "rzeka": "Jarka",
      "wojewodztwo": "warmińsko-mazurskie",
      "lon": "22.3681",
      "lat": "54.3092",
      "stan_wody": "50",
      "stan_wody_data_pomiaru": "2025-09-04 22:00:00",
      "temperatura_wody": null,
      "temperatura_wody_data_pomiaru": null,
      "przelyw": "0.23",
      "przeplyw_data": "2025-09-04 21:50:00",
      "zjawisko_lodowe": "0",
      "zjawisko_lodowe_data_pomiaru": "2025-01-09 10:10:00",
      "zjawisko_zarastania": "211",
      "zjawisko_zarastania_data_pomiaru": "2025-07-23 10:00:00"
    }
  },
  {
    "timestamp": "2025-09-04T23:21:13.399730+00:00",
    "data": {
      "id_stacji": "154220050",
      "stacja": "Jurkiszki",
      "rzeka": "Jarka",
      "wojewodztwo": "warmińsko-mazurskie",
      "lon": "22.3681",
      "lat": "54.3092",
      "stan_wody": "50",
      "stan_wody_data_pomiaru": "2025-09-04 23:00:00",
      "temperatura_wody": null,
      "temperatura_wody_data_pomiaru": null,
      "przelyw": "0.23",
      "przeplyw_data": "2025-09-04 22:50:00",
      "zjawisko_lodowe": "0",
      "zjawisko_lodowe_data_pomiaru": "2025-01-09 10:10:00",
      "zjawisko_zarastania": "211",
      "zjawisko_zarastania_data_pomiaru": "2025-07-23 10:00:00"
    }
  },
  {
    "timestamp": "2025-09-05T01:51:12.645525+00:00",
    "data": {
      "id_stacji": "154220050",
      "stacja": "Jurkiszki",
      "rzeka": "Jarka",
      "wojewodztwo": "warmińsko-mazurskie",
      "lon": "22.3681",
      "lat": "54.3092",
      "stan_wody": "50",
      "stan_wody_data_pomiaru": "2025-09-05 01:30:00",
      "temperatura_wody": null,
      "temperatura_wody_data_pomiaru": null,
      "przelyw": "0.23",
      "przeplyw_data": "2025-09-05 01:30:00",
      "zjawisko_lodowe": "0",
      "zjawisko_lodowe_data_pomiaru": "2025-01-09 10:10:00",
      "zjawisko_zarastania": "211",
      "zjawisko_zarastania_data_pomiaru": "2025-07-23 10:00:00"
    }
  },
  {
    "timestamp": "2025-09-05T03:02:25.365570+00:00",
    "data": {
      "id_stacji": "154220050",
      "stacja": "Jurkiszki",
      "rzeka": "Jarka",
      "wojewodztwo": "warmińsko-mazurskie",
      "lon": "22.3681",
      "lat": "54.3092",
      "stan_wody": "50",
      "stan_wody_data_pomiaru": "2025-09-05 02:30:00",
      "temperatura_wody": null,
      "temperatura_wody_data_pomiaru": null,
      "przelyw": "0.23",
      "przeplyw_data": "2025-09-05 02:30:00",
      "zjawisko_lodowe": "0",
      "zjawisko_lodowe_data_pomiaru": "2025-01-09 10:10:00",
      "zjawisko_zarastania": "211",
      "zjawisko_zarastania_data_pomiaru": "2025-07-23 10:00:00"
    }
  },
  {
    "timestamp": "2025-09-05T03:48:16.079013+00:00",
    "data": {
      "id_stacji": "154220050",
      "stacja": "Jurkiszki",
      "rzeka": "Jarka",
      "wojewodztwo": "warmińsko-mazurskie",
      "lon": "22.3681",
      "lat": "54.3092",
      "stan_wody": "50",
      "stan_wody_data_pomiaru": "2025-09-05 03:30:00",
      "temperatura_wody": null,
      "temperatura_wody_data_pomiaru": null,
      "przelyw": "0.23",
      "przeplyw_data": "2025-09-05 03:30:00",
      "zjawisko_lodowe": "0",
      "zjawisko_lodowe_data_pomiaru": "2025-01-09 10:10:00",
      "zjawisko_zarastania": "211",
      "zjawisko_zarastania_data_pomiaru": "2025-07-23 10:00:00"
    }
  },
  {
    "timestamp": "2025-09-05T04:28:25.105763+00:00",
    "data": {
      "id_stacji": "154220050",
      "stacja": "Jurkiszki",
      "rzeka": "Jarka",
      "wojewodztwo": "warmińsko-mazurskie",
      "lon": "22.3681",
      "lat": "54.3092",
      "stan_wody": "50",
      "stan_wody_data_pomiaru": "2025-09-05 04:00:00",
      "temperatura_wody": null,
      "temperatura_wody_data_pomiaru": null,
      "przelyw": "0.23",
      "przeplyw_data": "2025-09-05 04:10:00",
      "zjawisko_lodowe": "0",
      "zjawisko_lodowe_data_pomiaru": "2025-01-09 10:10:00",
      "zjawisko_zarastania": "211",
      "zjawisko_zarastania_data_pomiaru": "2025-07-23 10:00:00"
    }
  },
  {
    "timestamp": "2025-09-05T04:45:11.895579+00:00",
    "data": {
      "id_stacji": "154220050",
      "stacja": "Jurkiszki",
      "rzeka": "Jarka",
      "wojewodztwo": "warmińsko-mazurskie",
      "lon": "22.3681",
      "lat": "54.3092",
      "stan_wody": "50",
      "stan_wody_data_pomiaru": "2025-09-05 04:30:00",
      "temperatura_wody": null,
      "temperatura_wody_data_pomiaru": null,
      "przelyw": "0.23",
      "przeplyw_data": "2025-09-05 04:10:00",
      "zjawisko_lodowe": "0",
      "zjawisko_lodowe_data_pomiaru": "2025-01-09 10:10:00",
      "zjawisko_zarastania": "211",
      "zjawisko_zarastania_data_pomiaru": "2025-07-23 10:00:00"
    }
  },
  {
    "timestamp": "2025-09-05T05:22:49.442337+00:00",
    "data": {
      "id_stacji": "154220050",
      "stacja": "Jurkiszki",
      "rzeka": "Jarka",
      "wojewodztwo": "warmińsko-mazurskie",
      "lon": "22.3681",
      "lat": "54.3092",
      "stan_wody": "50",
      "stan_wody_data_pomiaru": "2025-09-05 05:00:00",
      "temperatura_wody": null,
      "temperatura_wody_data_pomiaru": null,
      "przelyw": "0.23",
      "przeplyw_data": "2025-09-05 04:50:00",
      "zjawisko_lodowe": "0",
      "zjawisko_lodowe_data_pomiaru": "2025-01-09 10:10:00",
      "zjawisko_zarastania": "211",
      "zjawisko_zarastania_data_pomiaru": "2025-07-23 10:00:00"
    }
  },
  {
    "timestamp": "2025-09-05T06:35:03.296039+00:00",
    "data": {
      "id_stacji": "154220050",
      "stacja": "Jurkiszki",
      "rzeka": "Jarka",
      "wojewodztwo": "warmińsko-mazurskie",
      "lon": "22.3681",
      "lat": "54.3092",
      "stan_wody": "50",
      "stan_wody_data_pomiaru": "2025-09-05 06:00:00",
      "temperatura_wody": null,
      "temperatura_wody_data_pomiaru": null,
      "przelyw": "0.23",
      "przeplyw_data": "2025-09-05 06:10:00",
      "zjawisko_lodowe": "0",
      "zjawisko_lodowe_data_pomiaru": "2025-01-09 10:10:00",
      "zjawisko_zarastania": "211",
      "zjawisko_zarastania_data_pomiaru": "2025-07-23 10:00:00"
    }
  }
]